[1,["a9d21vrdRAspLHnB271anL","aa2mDU71FOlJlOpgmpsaom","436ZANdq5BqJsm/RdhSWpG","5eWYj2fHhEKoSEmdVs6kjF","bfjxQKetZGKJAsPdli/pZJ","98ELwEkIZBTIJOPtXxtxiE","21mM7GzGJO2YPn8r5LY8ow","40GUQPRVVGv7CJ9/ROKsH6","8eOa3ofs1GbI7LR/39Rncj","b2dAtp7aVK/qXB+/nOL2cI","caYLh0Q7tCuJlcQpRxh/EE","degTNVQX9IvJ4Y+lUrCs/H","1cCkuC/A1E3Yj+CD5k2Z/4","e64MaoGb5GzZ7IwJDv8GHg","db6Cw7nSxJqbPLUCyLF1Wn","e9geE6VD1Kgo4pdvRZ17LM"],["value"],[["cc.AnimationClip",["_name","_duration","sample","curveData"],0,11]],[[0,0,1,2,3,4]],[[0,"BtnSpinTab",0.4,40,[{},"comps",11,[{},"cc.Sprite",11,[{},"spriteFrame",12,[[[{"frame":0},"value",6,0],[{"frame":0.025},"value",6,1],[{"frame":0.05},"value",6,2],[{"frame":0.075},"value",6,3],[{"frame":0.1},"value",6,4],[{"frame":0.125},"value",6,5],[{"frame":0.15},"value",6,6],[{"frame":0.175},"value",6,7],[{"frame":0.2},"value",6,8],[{"frame":0.225},"value",6,9],[{"frame":0.25},"value",6,10],[{"frame":0.275},"value",6,11],[{"frame":0.3},"value",6,12],[{"frame":0.325},"value",6,13],[{"frame":0.35},"value",6,14],[{"frame":0.375},"value",6,15]],11,11,11,11,11,11,11,11,11,11,11,11,11,11,11,11]]],"paths",11,[{},"click_effect-click_a",11,[{},"props",11,[{"opacity":[{"frame":0,"value":255},{"frame":0.375,"value":0}]},"scale",12,[[[{"frame":0},"value",8,[0,0,0]],[{"frame":0.375},"value",8,[0,2,2]]],11,11]]]]]]],0,0,[0,0,0,0,0,0,0,0,0,0,0,0,0,0,0,0],[0,0,0,0,0,0,0,0,0,0,0,0,0,0,0,0],[0,1,2,3,4,5,6,7,8,9,10,11,12,13,14,15]]