[1,["11OcfR0z9BzJeHOhbtJgmX"],0,[["sp.SkeletonData",["_name","_atlasText","textureNames","_skeletonJson","textures"],-1,3]],[[0,0,1,2,3,4,5]],[[0,"Fish_14","\r\n1998_Fish_2.png\r\nsize: 2033,952\r\nformat: RGBA8888\r\nfilter: Linear,Linear\r\nrepeat: none\r\n14_15/Beard\r\n  rotate: true\r\n  xy: 1562, 2\r\n  size: 34, 48\r\n  orig: 34, 48\r\n  offset: 0, 0\r\n  index: -1\r\n14_15/Body\r\n  rotate: true\r\n  xy: 807, 11\r\n  size: 97, 114\r\n  orig: 97, 114\r\n  offset: 0, 0\r\n  index: -1\r\n14_15/Bulb\r\n  rotate: false\r\n  xy: 655, 181\r\n  size: 44, 44\r\n  orig: 44, 44\r\n  offset: 0, 0\r\n  index: -1\r\n14_15/Dorsal Spike 1\r\n  rotate: false\r\n  xy: 164, 12\r\n  size: 58, 11\r\n  orig: 58, 11\r\n  offset: 0, 0\r\n  index: -1\r\n14_15/Dorsal Spike 2\r\n  rotate: false\r\n  xy: 164, 2\r\n  size: 36, 8\r\n  orig: 36, 8\r\n  offset: 0, 0\r\n  index: -1\r\n14_15/Dorsal Spike 3\r\n  rotate: true\r\n  xy: 2010, 723\r\n  size: 32, 10\r\n  orig: 32, 10\r\n  offset: 0, 0\r\n  index: -1\r\n14_15/Dorsal Spike 4\r\n  rotate: false\r\n  xy: 1612, 24\r\n  size: 19, 12\r\n  orig: 19, 12\r\n  offset: 0, 0\r\n  index: -1\r\n14_15/Fin\r\n  rotate: false\r\n  xy: 590, 227\r\n  size: 18, 20\r\n  orig: 18, 20\r\n  offset: 0, 0\r\n  index: -1\r\n14_15/Lateral Spike 1\r\n  rotate: false\r\n  xy: 1971, 407\r\n  size: 17, 8\r\n  orig: 17, 8\r\n  offset: 0, 0\r\n  index: -1\r\n14_15/Lateral Spike 2\r\n  rotate: false\r\n  xy: 1931, 2\r\n  size: 10, 12\r\n  orig: 10, 12\r\n  offset: 0, 0\r\n  index: -1\r\n14_15/Pectoral Spike\r\n  rotate: false\r\n  xy: 1931, 407\r\n  size: 18, 8\r\n  orig: 18, 8\r\n  offset: 0, 0\r\n  index: -1\r\n14_15/Pelvic Spike\r\n  rotate: false\r\n  xy: 2010, 668\r\n  size: 13, 19\r\n  orig: 13, 19\r\n  offset: 0, 0\r\n  index: -1\r\n14_15/bong\r\n  rotate: false\r\n  xy: 1105, 50\r\n  size: 108, 123\r\n  orig: 108, 123\r\n  offset: 0, 0\r\n  index: -1\r\n14_15/traicau\r\n  rotate: false\r\n  xy: 1258, 68\r\n  size: 4, 4\r\n  orig: 4, 4\r\n  offset: 0, 0\r\n  index: -1\r\n",["1998_Fish_2.png"],{"skeleton":{"hash":"AaDw+DNVdODHDHEEk4i6gNEwS+c","spine":"3.7.94","width":142.26,"height":123.89,"images":"../../images/","audio":"D:/TUAN/SPINE/Anim_Ca_2/projects/x30_x20x60"},"bones":[{"name":"root"},{"name":"Rotator","parent":"root","rotation":-90,"scaleX":0.55,"scaleY":0.55},{"name":"xuong_tyle","parent":"Rotator","scaleX":1.2,"scaleY":1.2},{"name":"3D Tilt","parent":"xuong_tyle","y":100,"color":"ff6400ff"},{"name":"Body","parent":"xuong_tyle"},{"name":"Center","parent":"Body","y":20,"color":"c8ff00ff"},{"name":"Left","parent":"Body","x":-48,"y":16.36,"color":"c8ff00ff"},{"name":"Right","parent":"Body","x":48,"y":16,"color":"c8ff00ff"},{"name":"Tail 1","parent":"Body","length":7.18,"rotation":-90,"x":-0.7,"y":-50.83,"color":"9600ffff"},{"name":"Tail 2","parent":"Tail 1","length":7.18,"x":7.18,"color":"9600ffff"},{"name":"Tail 3","parent":"Tail 2","length":7.18,"x":7.18,"color":"9600ffff"},{"name":"Tail 4","parent":"Tail 3","length":7.18,"x":7.18,"color":"9600ffff"},{"name":"Head","parent":"Body","y":80,"color":"9600ffff"},{"name":"Dorsal Spike 1","parent":"Body","y":10.49,"color":"00ffffff"},{"name":"Dorsal Spike 2","parent":"Body","y":0.73,"color":"00ffffff"},{"name":"Dorsal Spike 3","parent":"Body","y":1,"color":"00ffffff"},{"name":"Dorsal Spike 4","parent":"Body","y":-19,"color":"00ffffff"},{"name":"Pelvic Spkie Left","parent":"Body","x":-28,"y":-18,"color":"00ffffff"},{"name":"Pelvic Spkie Right","parent":"Body","x":28,"y":-18,"scaleX":-1,"color":"00ffffff"},{"name":"Pectoral Spike Left","parent":"Body","x":-49,"y":33.75,"color":"00ffffff"},{"name":"Pectoral Spike Right","parent":"Body","x":49,"y":33.75,"scaleX":-1,"color":"00ffffff"},{"name":"Lateral Spike Left 1","parent":"Body","x":-62.5,"y":14,"color":"00ffffff"},{"name":"Lateral Spike Right 1","parent":"Body","x":63.5,"y":14,"scaleX":-1,"color":"00ffffff"},{"name":"Lateral Spike Left 2","parent":"Body","x":-45.25,"y":-4.5,"color":"00ffffff"},{"name":"Lateral Spike Right 2","parent":"Body","x":45.25,"y":-4.5,"scaleX":-1,"color":"00ffffff"},{"name":"Beard Left All","parent":"Body","x":-22.5,"y":56,"color":"9600ffff"},{"name":"Beard Left 1","parent":"Beard Left All","length":13.55,"rotation":98,"x":-0.03,"y":-0.12,"color":"9600ffff"},{"name":"Beard Left 2","parent":"Beard Left 1","length":13.55,"rotation":5,"x":13.54,"color":"9600ffff"},{"name":"Beard Left 3","parent":"Beard Left 2","length":13.55,"rotation":5,"x":13.54,"color":"9600ffff"},{"name":"Beard Left 4","parent":"Beard Left 3","length":13.55,"rotation":5,"x":13.54,"color":"9600ffff"},{"name":"Beard Left 5","parent":"Beard Left 4","length":13.55,"rotation":20,"x":13.54,"color":"9600ffff"},{"name":"Beard Left 6","parent":"Beard Left 5","length":5.3,"rotation":24,"x":13.54,"color":"9600ffff"},{"name":"Beard Left 7","parent":"Beard Left 6","length":5.3,"rotation":40,"x":5.3,"color":"9600ffff"},{"name":"Beard Left 8","parent":"Beard Left 7","length":5.3,"rotation":20,"x":5.3,"color":"9600ffff"},{"name":"Beard Left 9","parent":"Beard Left 8","length":5.3,"rotation":5,"x":5.3,"color":"9600ffff"},{"name":"Beard Left 10","parent":"Beard Left 9","length":5.3,"rotation":5,"x":5.3,"color":"9600ffff"},{"name":"Beard Right All","parent":"Body","x":22.5,"y":56,"scaleX":-1,"color":"9600ffff"},{"name":"Beard Left 11","parent":"Beard Right All","length":13.55,"rotation":98,"x":-0.03,"y":-0.12,"color":"9600ffff"},{"name":"Beard Left 12","parent":"Beard Left 11","length":13.55,"rotation":5,"x":13.54,"color":"9600ffff"},{"name":"Beard Left 13","parent":"Beard Left 12","length":13.55,"rotation":5,"x":13.54,"color":"9600ffff"},{"name":"Beard Left 14","parent":"Beard Left 13","length":13.55,"rotation":5,"x":13.54,"color":"9600ffff"},{"name":"Beard Left 15","parent":"Beard Left 14","length":13.55,"rotation":20,"x":13.54,"color":"9600ffff"},{"name":"Beard Left 16","parent":"Beard Left 15","length":5.3,"rotation":24,"x":13.54,"color":"9600ffff"},{"name":"Beard Left 17","parent":"Beard Left 16","length":5.3,"rotation":40,"x":5.3,"color":"9600ffff"},{"name":"Beard Left 18","parent":"Beard Left 17","length":5.3,"rotation":20,"x":5.3,"color":"9600ffff"},{"name":"Beard Left 19","parent":"Beard Left 18","length":5.3,"rotation":5,"x":5.3,"color":"9600ffff"},{"name":"Beard Left 20","parent":"Beard Left 19","length":5.3,"rotation":5,"x":5.3,"color":"9600ffff"},{"name":"Fin Left All","parent":"Body","x":-56.5,"y":1.75,"color":"9600ffff"},{"name":"Fin Left","parent":"Fin Left All","rotation":-138,"color":"9600ffff"},{"name":"Fin Left Fan 4","parent":"Fin Left","length":23.02,"rotation":40,"color":"9600ffff"},{"name":"Fin Left Fan 3","parent":"Fin Left","length":23.02,"rotation":12.5,"color":"9600ffff"},{"name":"Fin Left Fan 2","parent":"Fin Left","length":23.02,"rotation":-12.5,"color":"9600ffff"},{"name":"Fin Left Fan 1","parent":"Fin Left","length":23.02,"rotation":-39.93,"color":"9600ffff"},{"name":"Fin Right All","parent":"Body","x":56.5,"y":1.75,"scaleX":-1,"color":"9600ffff"},{"name":"Fin Right","parent":"Fin Right All","rotation":-138,"color":"9600ffff"},{"name":"Fin Right Fan 4","parent":"Fin Right","length":23.02,"rotation":40,"color":"9600ffff"},{"name":"Fin Right Fan 3","parent":"Fin Right","length":23.02,"rotation":12.5,"color":"9600ffff"},{"name":"Fin Right Fan 2","parent":"Fin Right","length":23.02,"rotation":-12.5,"color":"9600ffff"},{"name":"Fin Right Fan 1","parent":"Fin Right","length":23.02,"rotation":-39.93,"color":"9600ffff"},{"name":"Bulb Right","parent":"Beard Left 20","x":5,"color":"9600ffff"},{"name":"Bulb Left","parent":"Beard Left 10","x":5,"color":"9600ffff"},{"name":"BONG","parent":"Rotator","x":130.87,"y":-57.36,"scaleX":0.8,"scaleY":0.8,"color":"ff0000ff"},{"name":"xuong_tyle2","parent":"BONG","x":-111.53,"y":-4.06,"scaleX":1.2,"scaleY":1.2},{"name":"Body2","parent":"xuong_tyle2"},{"name":"Center2","parent":"Body2","y":20,"color":"c8ff00ff"},{"name":"Left2","parent":"Body2","x":-31.14,"y":6.41,"color":"c8ff00ff"},{"name":"Right2","parent":"Body2","x":30.44,"y":11.89,"color":"c8ff00ff"},{"name":"Tail 5","parent":"Body2","length":7.18,"rotation":-90,"x":12.9,"y":-40.63,"color":"9600ffff"},{"name":"Tail 6","parent":"Tail 5","length":7.18,"x":7.18,"color":"9600ffff"},{"name":"Tail 7","parent":"Tail 6","length":7.18,"x":7.18,"color":"9600ffff"},{"name":"Tail 8","parent":"Tail 7","length":7.18,"x":7.18,"color":"9600ffff"},{"name":"Head2","parent":"Body2","y":80,"color":"9600ffff"},{"name":"Beard Left All2","parent":"Body2","x":-15.68,"y":22.16,"scaleX":0.657,"scaleY":0.657,"color":"9600ffff"},{"name":"Beard Left 21","parent":"Beard Left All2","length":13.55,"rotation":98,"x":-0.03,"y":-0.12,"color":"9600ffff"},{"name":"Beard Left 22","parent":"Beard Left 21","length":13.55,"rotation":5,"x":13.54,"color":"9600ffff"},{"name":"Beard Left 23","parent":"Beard Left 22","length":13.55,"rotation":5,"x":13.54,"color":"9600ffff"},{"name":"Beard Left 24","parent":"Beard Left 23","length":13.55,"rotation":5,"x":13.54,"color":"9600ffff"},{"name":"Beard Left 25","parent":"Beard Left 24","length":13.55,"rotation":20,"x":13.54,"color":"9600ffff"},{"name":"Beard Left 26","parent":"Beard Left 25","length":5.3,"rotation":24,"x":13.54,"color":"9600ffff"},{"name":"Beard Left 27","parent":"Beard Left 26","length":5.3,"rotation":40,"x":5.3,"color":"9600ffff"},{"name":"Beard Left 28","parent":"Beard Left 27","length":5.3,"rotation":20,"x":5.3,"color":"9600ffff"},{"name":"Beard Left 29","parent":"Beard Left 28","length":5.3,"rotation":5,"x":5.3,"color":"9600ffff"},{"name":"Beard Left 30","parent":"Beard Left 29","length":5.3,"rotation":5,"x":5.3,"color":"9600ffff"},{"name":"Bulb Left2","parent":"Beard Left 30","x":5,"color":"9600ffff"},{"name":"Beard Right All2","parent":"Body2","x":22.5,"y":56,"scaleX":-1,"color":"9600ffff"},{"name":"Beard Left 31","parent":"Beard Right All2","length":13.55,"rotation":98,"x":7.61,"y":-31.78,"scaleX":0.613,"scaleY":0.613,"color":"9600ffff"},{"name":"Beard Left 32","parent":"Beard Left 31","length":13.55,"rotation":5,"x":13.54,"color":"9600ffff"},{"name":"Beard Left 33","parent":"Beard Left 32","length":13.55,"rotation":5,"x":13.54,"color":"9600ffff"},{"name":"Beard Left 34","parent":"Beard Left 33","length":13.55,"rotation":5,"x":13.54,"color":"9600ffff"},{"name":"Beard Left 35","parent":"Beard Left 34","length":13.55,"rotation":20,"x":13.54,"color":"9600ffff"},{"name":"Beard Left 36","parent":"Beard Left 35","length":5.3,"rotation":24,"x":13.54,"color":"9600ffff"},{"name":"Beard Left 37","parent":"Beard Left 36","length":5.3,"rotation":40,"x":5.3,"color":"9600ffff"},{"name":"Beard Left 38","parent":"Beard Left 37","length":5.3,"rotation":20,"x":5.3,"color":"9600ffff"},{"name":"Beard Left 39","parent":"Beard Left 38","length":5.3,"rotation":5,"x":5.3,"color":"9600ffff"},{"name":"Beard Left 40","parent":"Beard Left 39","length":5.3,"rotation":5,"x":5.3,"color":"9600ffff"},{"name":"Bulb Right2","parent":"Beard Left 40","x":5,"color":"9600ffff"},{"name":"Fin Left All2","parent":"Body2","x":-56.5,"y":1.75,"color":"9600ffff"},{"name":"Fin Left2","parent":"Fin Left All2","rotation":-138,"x":18.09,"y":-15.66,"color":"9600ffff"},{"name":"Fin Left Fan 5","parent":"Fin Left2","length":23.02,"rotation":40,"color":"9600ffff"},{"name":"Fin Left Fan 6","parent":"Fin Left2","length":23.02,"rotation":12.5,"color":"9600ffff"},{"name":"Fin Left Fan 7","parent":"Fin Left2","length":23.02,"rotation":-12.5,"color":"9600ffff"},{"name":"Fin Left Fan 8","parent":"Fin Left2","length":23.02,"rotation":-39.93,"color":"9600ffff"},{"name":"Fin Right All2","parent":"Body2","x":56.5,"y":1.75,"scaleX":-1,"color":"9600ffff"},{"name":"Fin Right2","parent":"Fin Right All2","rotation":-138,"x":19.95,"y":-16.41,"color":"9600ffff"},{"name":"Fin Right Fan 5","parent":"Fin Right2","length":23.02,"rotation":40,"color":"9600ffff"},{"name":"Fin Right Fan 6","parent":"Fin Right2","length":23.02,"rotation":12.5,"color":"9600ffff"},{"name":"Fin Right Fan 7","parent":"Fin Right2","length":23.02,"rotation":-12.5,"color":"9600ffff"},{"name":"Fin Right Fan 8","parent":"Fin Right2","length":23.02,"rotation":-39.93,"color":"9600ffff"}],"slots":[{"name":"bong","bone":"BONG","attachment":"bong"},{"name":"Fin Left","bone":"Fin Left","attachment":"Fin Left"},{"name":"Fin Right","bone":"Fin Right","attachment":"Fin Right"},{"name":"Body","bone":"Body","attachment":"Body"},{"name":"Beard Left","bone":"Beard Left 10","attachment":"Beard Left"},{"name":"Beard Left2","bone":"Beard Left 20","attachment":"Beard Left"},{"name":"Bulb Left","bone":"Bulb Left","attachment":"Bulb Left"},{"name":"Bulb Right","bone":"Bulb Right","attachment":"Bulb Right"},{"name":"Pectoral Spike Right","bone":"Pectoral Spike Right","attachment":"Pectoral Spike Right2"},{"name":"Pectoral Spike Left","bone":"Pectoral Spike Left","attachment":"Pectoral Spike Left2"},{"name":"Lateral Spike Right 1","bone":"Lateral Spike Right 1","attachment":"Lateral Spike Right 1"},{"name":"Lateral Spike Left 1","bone":"Lateral Spike Left 1","attachment":"Lateral Spike Left 1"},{"name":"Lateral Spike Right 2","bone":"Lateral Spike Right 2","attachment":"Lateral Spike Right 2"},{"name":"Lateral Spike Left 2","bone":"Lateral Spike Left 2","attachment":"Lateral Spike Left 3"},{"name":"Pelvic Spike Right","bone":"Pelvic Spkie Right","attachment":"Pelvic Spike Right"},{"name":"Pelvic Spike Left","bone":"Pelvic Spkie Left","attachment":"Pelvic Spike Left"},{"name":"Dorsal Spike 1","bone":"Dorsal Spike 1","attachment":"Dorsal Spike 1"},{"name":"Dorsal Spike 2","bone":"Dorsal Spike 2","attachment":"Dorsal Spike 2"},{"name":"Dorsal Spike 3","bone":"Dorsal Spike 3","attachment":"Dorsal Spike 3"},{"name":"Dorsal Spike 4","bone":"Dorsal Spike 4","attachment":"Dorsal Spike 4"},{"name":"traicau","bone":"Beard Left 20","attachment":"traicau"},{"name":"traicau2","bone":"Beard Left 10","attachment":"traicau"}],"transform":[{"name":"-10","order":22,"target":"3D Tilt","x":38.42,"y":-123.24,"scaleX":-0.24,"scaleY":-0.24,"rotateMix":0,"translateMix":-0.1,"scaleMix":0,"shearMix":0,"bones":["Right2"]},{"name":"25","order":20,"target":"3D Tilt","x":0.02,"y":-120.04,"scaleX":-0.24,"scaleY":-0.24,"rotateMix":0,"translateMix":0.25,"scaleMix":0,"shearMix":0,"bones":["Center2"]},{"name":"Beard Left","order":16,"target":"Center","x":-22.5,"y":36,"rotateMix":0,"translateMix":0.05,"scaleMix":0,"shearMix":0,"bones":["Beard Left All"]},{"name":"Beard Right","order":17,"target":"Center","x":22.5,"y":36,"rotateMix":0,"translateMix":0.05,"scaleMix":0,"shearMix":0,"bones":["Beard Right All"]},{"name":"Center","order":0,"target":"3D Tilt","y":-80,"rotateMix":0,"translateMix":0.25,"scaleMix":0,"shearMix":0,"bones":["Center"]},{"name":"Dorsal Spike 1","order":4,"target":"Center","y":4.75,"rotateMix":0,"translateMix":0.34,"scaleMix":0,"shearMix":0,"bones":["Dorsal Spike 1"]},{"name":"Dorsal Spike 2","order":5,"target":"3D Tilt","y":-84.5,"rotateMix":0,"translateMix":0.11,"scaleMix":0,"shearMix":0,"bones":["Dorsal Spike 2"]},{"name":"Dorsal Spike 3","order":6,"target":"Center","y":-19,"rotateMix":0,"translateMix":0.5,"scaleMix":0,"shearMix":0,"bones":["Dorsal Spike 3"]},{"name":"Dorsal Spike 4","order":7,"target":"3D Tilt","y":-119,"rotateMix":0,"translateMix":0.13,"scaleMix":0,"shearMix":0,"bones":["Dorsal Spike 4"]},{"name":"Fin Left","order":18,"target":"Left","x":-8.5,"y":-14.25,"rotateMix":0,"translateMix":0.5,"scaleMix":0,"shearMix":0,"bones":["Fin Left All"]},{"name":"Fin Right","order":19,"target":"Right","x":8.5,"y":-14.25,"rotateMix":0,"translateMix":0.5,"scaleMix":0,"shearMix":0,"bones":["Fin Right All"]},{"name":"Lateral Spike Left 1","order":12,"target":"Left","x":-14.6,"y":-2,"rotateMix":0,"translateMix":0.15,"scaleMix":0,"shearMix":0,"bones":["Lateral Spike Left 1"]},{"name":"Lateral Spike Left 2","order":14,"target":"Left","x":2.5,"y":-20.5,"rotateMix":0,"translateMix":-0.4,"scaleMix":0,"shearMix":0,"bones":["Lateral Spike Left 2"]},{"name":"Lateral Spike Right 1","order":13,"target":"Right","x":15.5,"y":-2,"rotateMix":0,"translateMix":0.15,"scaleMix":0,"shearMix":0,"bones":["Lateral Spike Right 1"]},{"name":"Lateral Spike Right 2","order":15,"target":"Right","x":-2.5,"y":-20.5,"rotateMix":0,"translateMix":-0.4,"scaleMix":0,"shearMix":0,"bones":["Lateral Spike Right 2"]},{"name":"Left","order":1,"target":"3D Tilt","x":-49,"y":-84,"rotateMix":0,"translateMix":-0.1,"scaleMix":0,"shearMix":0,"bones":["Left"]},{"name":"Pectoral Spike Left","order":10,"target":"Center","x":-49,"y":13.75,"rotateMix":0,"translateMix":0.05,"scaleMix":0,"shearMix":0,"bones":["Pectoral Spike Left"]},{"name":"Pectoral Spike Right","order":11,"target":"Center","x":49,"y":13.75,"rotateMix":0,"translateMix":0.05,"scaleMix":0,"shearMix":0,"bones":["Pectoral Spike Right"]},{"name":"Pelvic Spike Left","order":8,"target":"Center","x":-28,"y":-38,"rotateMix":0,"translateMix":0.35,"scaleMix":0,"shearMix":0,"bones":["Pelvic Spkie Left"]},{"name":"Pelvic Spike Right","order":9,"target":"Center","x":28,"y":-38,"rotateMix":0,"translateMix":0.35,"scaleMix":0,"shearMix":0,"bones":["Pelvic Spkie Right"]},{"name":"Right","order":2,"target":"3D Tilt","x":48,"y":-84,"rotateMix":0,"translateMix":-0.1,"scaleMix":0,"shearMix":0,"bones":["Right"]},{"name":"Tail","order":3,"target":"Center","rotation":-90,"y":-71,"rotateMix":0,"translateMix":0.5,"scaleMix":0,"shearMix":0,"bones":["Tail 1"]},{"name":"duoi","order":21,"target":"3D Tilt","rotation":-90,"x":-0.54,"y":-176.66,"scaleX":-0.24,"scaleY":-0.24,"rotateMix":0,"translateMix":0.24,"scaleMix":0,"shearMix":0,"bones":["Tail 5"]}],"skins":{"default":{"Beard Left":{"Beard Left":{"type":"mesh","path":"14_15/Beard","hull":23,"width":49,"height":69,"uvs":[0.82741,1,0.76741,0.83464,0.70341,0.66989,0.64341,0.5023,0.57541,0.34607,0.48341,0.20262,0.42541,0.1316,0.34941,0.09042,0.25141,0.0961,0.17541,0.13444,0.09341,0.18984,0,0.25091,0,0.10746,0.09541,0.05065,0.24941,0,0.43141,0,0.55941,0.03644,0.67941,0.12308,0.82141,0.27931,0.92541,0.44833,1,0.64291,1,0.83038,1,1],"triangles":[11,12,10,10,13,9,10,12,13,9,13,8,13,14,8,8,14,7,6,7,15,7,14,15,4,5,17,5,16,17,5,6,16,6,15,16,3,4,18,4,17,18,2,3,19,3,18,19,1,2,20,2,19,20,0,21,22,0,1,21,21,1,20],"vertices":[1,26,-2.74,4.88,1,2,26,8.97,6.19,0.92757,27,-4.01,6.57,0.07243,3,26,20.66,7.71,0.00451,27,7.77,7.06,0.95052,28,-5.13,7.53,0.04498,3,27,19.7,7.31,0.03004,28,6.77,6.75,0.9541,29,-6.15,7.31,0.01586,3,28,18.06,6.58,0.06322,29,5.07,6.16,0.93295,30,-5.85,8.68,0.00384,2,29,15.95,6.43,0.14542,30,4.46,5.22,0.85458,3,30,9.98,3.96,0.86835,31,-1.64,5.06,0.12931,32,-2.06,8.34,0.00234,4,30,14.6,4.74,0.13551,31,2.9,3.9,0.58376,32,0.67,4.53,0.25581,33,-2.81,5.84,0.02491,4,31,7.17,6.13,0.0368,32,5.37,3.49,0.29329,33,1.26,3.26,0.66393,34,-3.74,3.6,0.00598,3,33,5.83,3.13,0.3472,34,0.8,3.07,0.65237,35,-4.21,3.45,0.00043,2,34,6.34,3.22,0.21457,35,1.32,3.11,0.78543,1,35,7.52,2.64,1,2,34,5.94,-4.07,0.57542,35,0.28,-4.11,0.42458,2,33,5.48,-3.85,0.47566,34,-0.16,-3.85,0.52434,2,32,3.52,-2.87,0.93548,33,-2.65,-2.09,0.06452,2,30,16.42,-2.46,0.12037,31,1.63,-3.42,0.87963,2,30,10.3,-5.32,0.98513,31,-5.12,-3.55,0.01487,2,29,17.24,-4.55,0.10631,30,1.92,-5.54,0.89369,2,28,18.7,-6.31,0.07434,29,4.59,-6.74,0.92566,3,27,20.21,-6.99,0.03296,28,6.03,-7.54,0.96638,29,-8.13,-6.86,0.00066,3,26,20.47,-6.94,0.0182,27,6.3,-7.52,0.97465,28,-7.86,-6.86,0.00714,2,26,7.66,-5.13,0.99166,27,-6.3,-4.6,0.00834,1,26,-3.92,-3.5,1],"edges":[0,2,2,4,4,6,6,8,8,10,10,12,12,14,14,16,16,18,18,20,20,22,22,24,24,26,26,28,28,30,30,32,32,34,34,36,36,38,38,40,40,42,42,44,0,44]}},"Beard Left2":{"Beard Left":{"type":"mesh","path":"14_15/Beard","hull":23,"width":49,"height":69,"uvs":[0.82741,1,0.76741,0.83464,0.70341,0.66989,0.64341,0.5023,0.57541,0.34607,0.48341,0.20262,0.42541,0.1316,0.34941,0.09042,0.25141,0.0961,0.17541,0.13444,0.09341,0.18984,0,0.25091,0,0.10746,0.09541,0.05065,0.24941,0,0.43141,0,0.55941,0.03644,0.67941,0.12308,0.82141,0.27931,0.92541,0.44833,1,0.64291,1,0.83038,1,1],"triangles":[11,12,10,10,13,9,10,12,13,9,13,8,13,14,8,8,14,7,6,7,15,7,14,15,4,5,17,5,16,17,5,6,16,6,15,16,3,4,18,4,17,18,2,3,19,3,18,19,1,2,20,2,19,20,0,21,22,0,1,21,21,1,20],"vertices":[1,37,-2.74,4.88,1,2,37,8.97,6.19,0.92757,38,-4.01,6.57,0.07243,3,37,20.66,7.71,0.00451,38,7.77,7.06,0.95052,39,-5.13,7.53,0.04498,3,38,19.7,7.31,0.03004,39,6.77,6.75,0.9541,40,-6.15,7.31,0.01586,3,39,18.06,6.58,0.06322,40,5.07,6.16,0.93295,41,-5.85,8.68,0.00384,2,40,15.95,6.43,0.14542,41,4.46,5.22,0.85458,3,41,9.98,3.96,0.86835,42,-1.64,5.06,0.12931,43,-2.06,8.34,0.00234,4,41,14.6,4.74,0.13551,42,2.9,3.9,0.58376,43,0.67,4.53,0.25581,44,-2.81,5.84,0.02491,4,42,7.17,6.13,0.0368,43,5.37,3.49,0.29329,44,1.26,3.26,0.66393,45,-3.74,3.6,0.00598,3,44,5.83,3.13,0.3472,45,0.8,3.07,0.65237,46,-4.21,3.45,0.00043,2,45,6.34,3.22,0.21457,46,1.32,3.11,0.78543,1,46,7.52,2.64,1,2,45,5.94,-4.07,0.57542,46,0.28,-4.11,0.42458,2,44,5.48,-3.85,0.47566,45,-0.16,-3.85,0.52434,2,43,3.52,-2.87,0.93548,44,-2.65,-2.09,0.06452,2,41,16.42,-2.46,0.12037,42,1.63,-3.42,0.87963,2,41,10.3,-5.32,0.98513,42,-5.12,-3.55,0.01487,2,40,17.24,-4.55,0.10631,41,1.92,-5.54,0.89369,2,39,18.7,-6.31,0.07434,40,4.59,-6.74,0.92566,3,38,20.21,-6.99,0.03296,39,6.03,-7.54,0.96638,40,-8.13,-6.86,0.00066,3,37,20.47,-6.94,0.0182,38,6.3,-7.52,0.97465,39,-7.86,-6.86,0.00714,2,37,7.66,-5.13,0.99166,38,-6.3,-4.6,0.00834,1,37,-3.92,-3.5,1],"edges":[0,2,2,4,4,6,6,8,8,10,10,12,12,14,14,16,16,18,18,20,20,22,22,24,24,26,26,28,28,30,30,32,32,34,34,36,36,38,38,40,40,42,42,44,0,44]}},"Body":{"Body":{"type":"mesh","path":"14_15/Body","hull":31,"width":139,"height":163,"uvs":[0.51009,1,0.48945,0.99999,0.45931,0.94484,0.44224,0.90085,0.47802,0.85217,0.47874,0.82787,0.3972,0.79866,0.33818,0.74198,0.30191,0.66721,0.04024,0.51538,0,0.44113,0.00001,0.27681,0.08158,0.17921,0.13768,0.09486,0.19517,0.09454,0.34998,0,0.5,0,0.65607,0,0.81211,0.09599,0.87108,0.09534,0.92043,0.17933,1,0.28143,1,0.44113,0.95976,0.51538,0.69814,0.66757,0.66098,0.74198,0.60185,0.80196,0.52068,0.82787,0.52075,0.85217,0.55773,0.90085,0.54152,0.94484,0.5745,0.74198,0.42854,0.74198,0.58643,0.66757,0.4153,0.66757,0.62528,0.51538,0.37472,0.51538,0.70643,0.36984,0.2953,0.36984,0.49988,0.92358,0.16207,0.40199,0.83867,0.40191,0.34976,0.66852,0.37801,0.74299,0.29411,0.5466,0.22391,0.42395,0.62286,0.74226,0.65111,0.66779,0.70847,0.54806,0.77781,0.42249,0.83603,0.33747,0.76497,0.21847,0.16569,0.3382,0.23589,0.22066,0.19052,0.18749,0.80606,0.18822,0.40032,0.08321,0.59375,0.0842,0.49993,0.05852,0.50109,0.24322],"triangles":[44,45,38,48,35,37,36,44,38,49,48,37,44,36,42,35,48,47,55,51,18,55,19,20,19,55,18,50,20,21,50,55,20,51,55,50,22,41,50,49,37,50,41,49,50,22,50,21,23,41,22,49,41,23,23,24,48,23,48,49,54,13,14,12,13,54,54,14,53,52,12,54,52,54,53,11,12,52,52,10,11,45,40,52,38,45,52,40,10,52,9,10,40,9,40,45,45,44,9,8,9,44,1,2,39,0,1,39,30,0,39,39,28,29,3,4,39,30,39,29,2,3,39,44,42,8,47,33,35,35,33,34,24,47,48,36,34,42,25,47,24,7,8,42,32,34,33,31,32,33,46,33,47,46,47,25,31,33,46,43,42,34,43,34,32,7,42,43,6,43,32,7,43,6,26,31,46,26,46,25,27,32,31,27,31,26,5,6,32,27,5,32,5,28,4,28,5,27,39,4,28,16,56,15,58,56,16,57,16,17,58,16,57,14,15,56,18,57,17,18,51,57,53,14,56,59,58,57,59,57,51,56,58,59,53,56,59,37,59,51,37,51,50,38,53,59,52,53,38,36,38,59,35,36,59,37,35,59,35,34,36],"vertices":[1,11,8.97,1.4,1,1,11,8.97,-1.47,1,2,10,7.16,-5.66,0.5,11,-0.02,-5.66,0.5,2,9,7.16,-8.03,0.5,10,-0.01,-8.03,0.5,2,8,6.4,-3.06,0.5,9,-0.77,-3.06,0.5,1,8,2.44,-2.96,1,2,8,-2.32,-14.29,0.925,6,34.71,-64.68,0.075,2,8,-11.56,-22.49,0.85,6,26.51,-55.44,0.15,2,8,-23.74,-27.53,0.75,6,21.47,-43.26,0.25,2,6,-14.91,-18.51,0.85,5,-63.91,-22.51,0.15,2,6,-20.5,-6.4,0.9,5,-69.5,-10.4,0.1,2,6,-20.5,20.38,0.9,5,-69.5,16.38,0.1,2,7,-106.16,36.29,0.85,5,-58.16,32.29,0.15,2,6,-1.36,50.04,0.8,5,-50.36,46.04,0.2,2,6,6.63,50.09,0.75,5,-42.37,46.09,0.25,1,12,-20.85,1.5,1,1,12,0,1.5,1,1,12,21.69,1.5,1,2,7,-4.62,49.85,0.75,5,43.38,45.85,0.25,2,7,3.58,49.96,0.8,5,51.58,45.96,0.2,2,7,10.44,36.27,0.85,5,58.44,32.27,0.15,2,7,21.5,19.63,0.9,5,69.5,15.63,0.1,2,7,21.5,-6.4,0.9,5,69.5,-10.4,0.1,2,7,15.91,-18.51,0.85,5,63.91,-22.51,0.15,2,8,-23.69,27.54,0.75,7,-20.46,-43.31,0.25,2,8,-11.56,22.38,0.85,7,-25.62,-55.44,0.15,2,8,-1.78,14.16,0.925,7,-33.84,-65.22,0.075,1,8,2.44,2.88,1,2,8,6.4,2.88,0.5,9,-0.77,2.88,0.5,2,9,7.16,8.02,0.5,10,-0.01,8.02,0.5,2,10,7.16,5.77,0.5,11,-0.02,5.77,0.5,1,8,-11.56,10.36,1,1,8,-11.56,-9.93,1,1,8,-23.69,12.01,1,1,8,-23.69,-11.77,1,2,12,17.41,-82.51,0.5,5,17.41,-22.51,0.5,2,12,-17.41,-82.51,0.5,5,-17.41,-22.51,0.5,2,12,28.69,-58.78,0.65,5,28.69,1.22,0.35,2,12,-28.45,-58.78,0.65,5,-28.45,1.22,0.35,2,10,3.69,-0.02,0.99963,11,-3.48,-0.02,0.00037,2,6,2.03,-0.02,0.7,5,-46.97,-4.02,0.3,2,7,-0.92,-0.01,0.7,5,47.08,-4.01,0.3,2,8,-23.53,-20.88,0.8,6,28.12,-43.47,0.2,2,8,-11.39,-16.96,0.9,6,32.04,-55.61,0.1,2,6,20.38,-23.6,0.5,5,-28.62,-27.6,0.5,2,6,10.62,-3.6,0.6,5,-38.38,-7.6,0.4,2,8,-11.51,17.08,0.9,7,-30.92,-55.49,0.1,2,8,-23.65,21,0.8,7,-27,-43.35,0.2,2,7,-19.02,-23.83,0.5,5,28.98,-27.83,0.5,2,7,-9.38,-3.37,0.6,5,38.62,-7.37,0.4,2,7,-1.29,10.49,0.7,5,46.71,6.49,0.3,3,12,36.83,-34.11,0.6375,7,-11.17,29.89,0.25,5,36.83,25.89,0.1125,2,6,2.53,10.37,0.7,5,-46.47,6.37,0.3,3,12,-36.71,-34.47,0.6375,6,12.29,29.53,0.25,5,-36.71,25.53,0.1125,2,6,5.98,34.94,0.7,5,-43.02,30.94,0.3,2,7,-5.46,34.82,0.7,5,42.54,30.82,0.3,1,12,-13.86,-12.06,1,1,12,13.03,-12.22,1,1,12,-0.01,-8.04,1,2,12,0.15,-38.15,0.75,5,0.15,21.85,0.25],"edges":[2,4,4,6,6,8,8,10,18,20,44,46,46,48,48,50,54,56,56,58,58,60,60,0,32,34,30,32,42,44,38,40,40,42,24,26,20,22,22,24,0,2,50,52,52,54,10,12,12,14,14,16,16,18,26,28,28,30,34,36,36,38]}},"Bulb Left":{"Bulb Left":{"path":"14_15/Bulb","width":63,"height":63}},"Bulb Right":{"Bulb Right":{"path":"14_15/Bulb","width":63,"height":63}},"Dorsal Spike 1":{"Dorsal Spike 1":{"path":"14_15/Dorsal Spike 1","y":7.33,"width":83,"height":15}},"Dorsal Spike 2":{"Dorsal Spike 2":{"path":"14_15/Dorsal Spike 2","y":4.71,"width":51,"height":12}},"Dorsal Spike 3":{"Dorsal Spike 3":{"path":"14_15/Dorsal Spike 3","y":-6.29,"width":45,"height":14}},"Dorsal Spike 4":{"Dorsal Spike 4":{"path":"14_15/Dorsal Spike 4","y":-1,"width":27,"height":17}},"Fin Left":{"Fin Left":{"type":"mesh","path":"14_15/Fin","hull":13,"width":25,"height":29,"uvs":[0.60978,0.06018,0.21515,0,0,0,0,0.30915,0,0.53646,0.22694,0.64946,0.33206,0.83322,0.56274,0.86091,0.72626,1,1,1,0.96774,0.71453,0.9584,0.37298,1,0,0.62751,0.18561,0.29068,0.27512,0.69535,0.29343,0.43672,0.47254,0.81819,0.35209,0.65095,0.63867],"triangles":[8,10,9,7,18,8,8,18,10,10,17,11,10,18,17,18,15,17,11,17,12,7,6,18,6,16,18,6,5,16,18,16,15,16,13,15,17,15,12,15,13,12,16,5,14,5,4,14,4,3,14,16,14,13,3,1,14,3,2,1,14,0,13,14,1,0,13,0,12],"vertices":[1,52,5.62,-2.65,1,2,52,17.82,-4.63,0.99974,51,13.67,-12.34,0.00026,2,52,21.65,-3.31,0.99828,51,17.68,-12.93,0.00172,2,52,21.9,3.78,0.62837,51,21.17,-6.76,0.37163,2,51,24.53,0.33,0.99829,50,22.38,-10.07,0.00171,2,51,21.31,5.01,0.47404,50,21.43,-4.47,0.52596,2,50,24.24,0.77,0.99041,49,21.86,-10.51,0.00959,2,50,21.55,5.93,0.42017,49,21.85,-4.69,0.57983,2,50,22.46,11.6,0.00043,49,25.27,-0.08,0.99957,1,49,24.5,5.41,1,1,49,19.85,4.83,1,1,49,5.74,2.92,1,4,52,-3.38,-3.87,0.06114,51,-4.79,-1.87,0.47587,50,-5.13,0.33,0.45707,49,-4.4,2.66,0.00592,2,52,5.76,0.96,0.67458,51,5.55,-1.81,0.32542,2,52,14.28,3.37,0.49927,51,14.22,-3.61,0.50073,2,51,6.15,1.93,0.24983,50,6.39,-0.85,0.75017,2,51,14.21,3.13,0.50755,50,14.2,-3.17,0.49245,2,50,6.13,2.6,0.12568,49,6.64,-0.53,0.87432,2,50,14.72,3.96,0.45574,49,14.88,-3.28,0.54426],"edges":[2,4,16,18,18,20,0,2,20,22,14,16,10,12,12,14,8,10,6,8,4,6,22,24,24,0]}},"Fin Right":{"Fin Right":{"type":"mesh","path":"14_15/Fin","hull":13,"width":25,"height":29,"uvs":[0.60978,0.06018,0.21515,0,0,0,0,0.30915,0,0.53646,0.22694,0.64946,0.33206,0.83322,0.56274,0.86091,0.72626,1,1,1,0.96774,0.71453,0.9584,0.37298,1,0,0.62751,0.18561,0.29068,0.27512,0.69535,0.29343,0.43672,0.47254,0.81819,0.35209,0.65095,0.63867],"triangles":[8,10,9,7,18,8,8,18,10,10,17,11,10,18,17,18,15,17,11,17,12,7,6,18,6,16,18,6,5,16,18,16,15,16,13,15,17,15,12,15,13,12,16,5,14,5,4,14,4,3,14,16,14,13,3,1,14,3,2,1,14,0,13,14,1,0,13,0,12],"vertices":[1,58,5.62,-2.65,1,2,58,17.82,-4.63,0.99974,57,13.67,-12.34,0.00026,2,58,21.65,-3.31,0.99828,57,17.68,-12.93,0.00172,2,58,21.9,3.78,0.62837,57,21.17,-6.76,0.37163,2,57,24.53,0.33,0.99829,56,22.38,-10.07,0.00171,2,57,21.31,5.01,0.47404,56,21.43,-4.47,0.52596,2,56,24.24,0.77,0.99041,55,21.86,-10.51,0.00959,2,56,21.55,5.93,0.42017,55,21.85,-4.69,0.57983,2,56,22.46,11.6,0.00043,55,25.27,-0.08,0.99957,1,55,24.5,5.41,1,1,55,19.85,4.83,1,1,55,5.74,2.92,1,4,58,-3.38,-3.87,0.06114,57,-4.79,-1.87,0.47587,56,-5.13,0.33,0.45707,55,-4.4,2.66,0.00592,2,58,5.76,0.96,0.67458,57,5.55,-1.81,0.32542,2,58,14.28,3.37,0.49927,57,14.22,-3.61,0.50073,2,57,6.15,1.93,0.24983,56,6.39,-0.85,0.75017,2,57,14.21,3.13,0.50755,56,14.2,-3.17,0.49245,2,56,6.13,2.6,0.12568,55,6.64,-0.53,0.87432,2,56,14.72,3.96,0.45574,55,14.88,-3.28,0.54426],"edges":[2,4,16,18,18,20,0,2,20,22,14,16,10,12,12,14,8,10,6,8,4,6,22,24,24,0]}},"Lateral Spike Left 1":{"Lateral Spike Left 1":{"path":"14_15/Lateral Spike 1","width":24,"height":12}},"Lateral Spike Left 2":{"Lateral Spike Left 3":{"path":"14_15/Lateral Spike 2","width":14,"height":17}},"Lateral Spike Right 1":{"Lateral Spike Right 1":{"path":"14_15/Lateral Spike 1","width":24,"height":12}},"Lateral Spike Right 2":{"Lateral Spike Right 2":{"path":"14_15/Lateral Spike 2","width":14,"height":17}},"Pectoral Spike Left":{"Pectoral Spike Left2":{"path":"14_15/Pectoral Spike","width":25,"height":12}},"Pectoral Spike Right":{"Pectoral Spike Right2":{"path":"14_15/Pectoral Spike","width":25,"height":12}},"Pelvic Spike Left":{"Pelvic Spike Left":{"path":"14_15/Pelvic Spike","width":19,"height":27}},"Pelvic Spike Right":{"Pelvic Spike Right":{"path":"14_15/Pelvic Spike","width":19,"height":27}},"bong":{"bong":{"type":"mesh","path":"14_15/bong","hull":70,"width":154,"height":176,"uvs":[0.36283,0.77427,0.39225,0.82576,0.44086,0.86717,0.44281,0.89281,0.4447,0.91754,0.47156,0.98864,0.53041,0.98864,0.54959,0.94552,0.55144,0.91277,0.55343,0.87724,0.61483,0.82911,0.65321,0.79106,0.71461,0.753,0.76194,0.74628,0.81439,0.74405,0.87068,0.71494,0.91417,0.66681,0.91929,0.60301,0.88859,0.55152,0.88219,0.48213,0.86044,0.42168,0.82207,0.37243,0.77857,0.32654,0.71717,0.31535,0.68775,0.29632,0.70566,0.25043,0.76194,0.25602,0.8387,0.26274,0.91545,0.25043,0.96406,0.22133,0.99351,0.17208,0.99351,0.10716,0.97557,0.04783,0.91673,0.01649,0.83742,0.01136,0.77218,0.01136,0.72357,0.05007,0.666,0.08477,0.61739,0.14521,0.58925,0.20342,0.5803,0.25379,0.51378,0.23476,0.43191,0.25155,0.40504,0.18103,0.36283,0.10156,0.30782,0.05343,0.25537,0.02209,0.19013,0.01136,0.11082,0.01136,0.04814,0.02209,0.00649,0.06798,0.00649,0.12171,0.00649,0.18327,0.01872,0.24035,0.08012,0.28737,0.15176,0.2952,0.22084,0.28737,0.28608,0.27281,0.28863,0.31199,0.22595,0.32654,0.17478,0.37131,0.13774,0.44037,0.10366,0.51119,0.08343,0.58573,0.08556,0.65189,0.11538,0.71898,0.18886,0.75253,0.22564,0.75598,0.27831,0.76092,0.32623,0.79073,0.11143,0.11417,0.20243,0.14788,0.29425,0.18877,0.35163,0.24974,0.64676,0.23683,0.6997,0.17413,0.77148,0.12819,0.87541,0.12819,0.27068,0.41324,0.39352,0.34234,0.56994,0.35492,0.74375,0.44068,0.81039,0.62935,0.19358,0.63278,0.35497,0.54441,0.24189,0.50226,0.75391,0.54716,0.51203,0.51692,0.53298,0.66993,0.49842,0.79545,0.49319,0.8834,0.50366,0.95303,0.68019,0.64351,0.8317,0.56201,0.32451,0.65411,0.36661,0.70776,0.62366,0.71487,0.6569,0.54747,0.5823,0.44213,0.38065,0.44277,0.26577,0.13648,0.08607,0.18953,0.1993,0.21318,0.23801,0.06553,0.82389,0.06936,0.81731,0.19528,0.91666,0.18314,0.94077,0.10196,0.50702,0.30549,0.68113,0.38049,0.49809,0.39768,0.43267,0.71775,0.56878,0.72551,0.44596,0.64574,0.60044,0.63078],"triangles":[26,105,27,28,27,106,105,26,75,28,106,29,106,27,105,105,75,76,29,106,30,105,77,106,105,76,77,106,107,30,106,77,107,107,31,30,76,104,77,77,104,33,77,33,107,107,32,31,107,33,32,33,104,34,104,36,35,104,76,36,104,35,34,75,37,76,37,36,76,74,38,75,38,37,75,24,74,25,40,39,74,74,75,25,75,26,25,39,38,74,24,40,74,108,41,40,87,98,97,97,81,86,81,98,109,81,97,98,87,110,98,110,80,98,98,80,109,81,109,22,81,21,20,81,22,21,22,109,23,110,108,80,109,80,24,24,80,40,109,24,23,80,108,40,56,55,102,102,55,101,56,102,57,55,54,101,54,53,101,57,102,72,100,102,71,53,52,101,102,101,71,101,70,71,70,101,51,101,52,51,71,70,103,51,50,70,50,49,70,49,48,70,70,47,103,70,48,47,103,47,46,100,71,103,103,46,45,100,45,44,100,103,45,100,72,102,72,44,43,72,100,44,58,57,73,57,72,73,73,43,42,73,72,43,108,42,41,84,85,99,84,99,87,99,85,78,99,110,87,85,61,78,78,61,60,99,79,110,99,78,79,60,59,78,78,58,79,78,59,58,110,79,108,58,73,79,79,42,108,79,73,42,64,63,83,63,62,83,83,62,85,62,61,85,66,65,83,65,64,83,94,83,85,0,69,95,95,69,68,95,68,94,68,67,94,94,67,83,67,66,83,95,94,113,94,84,113,84,94,85,17,82,93,17,93,18,82,86,93,18,93,19,93,86,19,19,81,20,19,86,81,14,82,15,15,82,16,16,82,17,92,86,82,11,96,12,13,12,92,12,96,92,14,13,82,13,92,82,96,114,92,114,97,92,92,97,86,114,87,97,8,91,90,4,3,90,8,90,9,3,2,90,5,91,6,6,91,7,5,4,91,4,90,91,7,91,8,9,90,89,90,2,89,9,89,10,2,1,89,89,112,10,11,112,96,11,10,112,1,111,89,1,0,111,89,88,112,89,111,88,0,95,111,96,112,114,111,113,88,111,95,113,112,88,114,114,88,87,88,113,87,113,84,87],"vertices":[9,67,-1.62,-17.58,0.52217,68,-8.79,-17.58,0.04446,104,14.59,57.48,0.00067,106,-36.72,46.56,0.00052,98,20.17,23.1,0.40095,100,-6.05,30.07,0.02173,73,-88.62,16.52,0.00721,74,-100.33,25.36,0,85,-106.68,-39.79,0.00229,8,67,5.93,-13.8,0.61918,69,-8.42,-13.8,0.00311,68,-1.24,-13.8,0.23298,98,27.12,27.89,0.1369,100,-5.62,38.5,0.00715,73,-100.8,12.43,0.00062,74,-112.82,22.35,0,85,-118.03,-31.97,0.00006,6,67,12.01,-7.57,0.20432,69,-2.34,-7.57,0.24731,68,4.83,-7.57,0.52899,98,32.27,34.92,0.01878,100,-8.06,46.86,0.0006,74,-123.97,15.18,0,7,67,15.77,-7.31,0.03357,70,-5.76,-7.31,0.03554,69,1.42,-7.31,0.62561,68,8.59,-7.31,0.30159,98,35.96,35.69,0.00364,100,-6.42,50.25,0.00006,74,-129.63,16.09,0,5,70,-2.13,-7.07,0.22083,69,5.04,-7.07,0.69966,68,12.22,-7.07,0.0794,98,39.52,36.43,0.0001,74,-135.09,16.98,0,2,70,8.29,-3.63,1,74,-151.73,15.43,0,2,70,8.29,3.93,0.99892,69,15.47,3.93,0.00108,3,70,1.97,6.39,0.64649,69,9.15,6.39,0.352,68,16.32,6.39,0.00151,5,70,-2.83,6.62,0.1271,69,4.34,6.62,0.74768,68,11.52,6.62,0.12422,104,38.07,36.34,0.00098,106,-5.66,52.33,0.00002,5,67,13.48,6.88,0.08468,69,-0.87,6.88,0.31879,68,6.31,6.88,0.58102,104,32.95,35.36,0.01493,106,-8,47.66,0.00058,6,67,6.43,14.76,0.57421,69,-7.93,14.76,0.00367,68,-0.75,14.76,0.25252,104,27.05,26.58,0.16121,106,-4.62,37.64,0.00833,73,-107.6,-30.51,0.00007,8,67,0.84,19.69,0.54482,68,-6.33,19.69,0.08251,104,22.21,20.92,0.35029,105,10.04,28.81,0.00001,106,-3.08,30.36,0.01824,100,-37.27,50.56,0.0004,73,-100.23,-39.11,0.00237,85,-102.19,21.01,0.00136,9,67,-4.74,27.57,0.2721,68,-11.91,27.57,0.01367,104,17.78,12.34,0.68398,105,10.07,19.16,0.00053,106,1.03,21.62,0.02366,98,10.8,67.37,0.00009,100,-46.88,49.58,0.0007,73,-93.49,-52.17,0.00331,85,-91.38,32.48,0.00196,7,67,-5.72,33.64,0.08023,68,-12.9,33.64,0.00246,104,17.65,6.19,0.90513,105,12.8,13.64,0.00166,106,5.83,17.77,0.00956,100,-52.65,51.72,0.00016,73,-93.29,-61.53,0.0008,3,104,18.26,-0.52,0.98833,105,16.44,7.97,0.01167,74,-113.6,-62.08,0,4,67,-10.32,47.59,0.00001,68,-17.5,47.59,0,105,17.16,-0.39,0.97614,106,15.72,6.9,0.02385,3,106,17.1,-1.99,0.87669,107,16.09,6.11,0.12331,74,-101.19,-84.94,0,4,105,7.42,-15,0.00487,107,16.41,-3.27,0.98408,74,-87.54,-89.12,0,85,-49.86,69.94,0.01106,4,105,-1.02,-16.18,0.04791,107,12.2,-10.67,0.83594,74,-74.99,-85.86,0,85,-38.54,61.85,0.11615,5,105,-9.78,-21.42,0.07244,107,11.01,-20.81,0.62103,74,-59.62,-88.13,0,85,-22.28,58.22,0.30651,86,-30.61,61.12,0.00002,5,105,-18.62,-24.3,0.06586,107,7.9,-29.57,0.47328,74,-45.52,-87.03,0,85,-8.58,51.69,0.45773,86,-17.53,53.42,0.00312,5,105,-27.36,-24.48,0.05153,107,2.72,-36.61,0.33951,74,-33.12,-82.2,0,85,1.97,42.09,0.59179,86,-7.85,42.94,0.01717,5,105,-36.08,-23.85,0.03589,107,-3.1,-43.14,0.22557,74,-21.23,-76.23,0,85,11.59,31.54,0.68448,86,0.8,31.59,0.05407,11,104,-45.74,3.08,0.00009,105,-41.99,-18.38,0.01886,106,-30.29,-34.41,0.00003,107,-11.03,-44.49,0.11533,74,-16.1,-65.1,0,85,12.45,18.43,0.68164,86,0.52,18.45,0.1829,87,-11.36,19.52,0.00078,92,20.79,50.19,0.00007,93,19.81,48.65,0.00004,94,18.69,47.2,0.00027,9,105,-46.46,-16.93,0.00547,107,-14.91,-47.15,0.03321,74,-10.67,-60.46,0,85,16.1,11.69,0.39456,86,3.57,11.42,0.51918,87,-8.93,12.25,0.03903,92,13.13,50.26,0.00142,93,12.18,49.39,0.00105,94,11.16,48.6,0.00608,10,105,-50.6,-22.71,0.00019,107,-12.85,-53.96,0.00115,85,27.51,13.88,0.00946,86,15.12,12.61,0.2289,87,2.68,12.42,0.53372,88,-9.74,13.32,0.06383,89,-17.32,20.48,0.00059,92,9.51,39.23,0.02529,93,7.61,38.71,0.02168,94,5.68,38.36,0.1152,7,86,16.47,24.4,0.0159,87,5.05,24.05,0.31601,88,-6.36,24.7,0.11816,89,-10.26,30.01,0.00856,92,19.73,33.2,0.05618,93,17.27,31.82,0.05347,94,14.7,30.65,0.43173,6,87,8.49,39.83,0.13566,88,-1.56,40.12,0.05193,89,-0.47,42.87,0.00083,92,33.54,24.81,0.02899,93,30.3,22.26,0.02209,94,26.84,19.99,0.7605,4,87,16.26,54.22,0.05223,88,7.43,53.77,0.01162,92,44.61,12.78,0.00422,94,35.65,6.22,0.93192,5,87,26.03,61.75,0.021,88,17.83,60.42,0.00141,91,50.55,17.63,0.00308,93,43.18,-2.68,0.00073,94,37.5,-5.98,0.97376,4,87,39.15,63.97,0.00407,91,53,4.55,0.02982,93,39.87,-15.57,0.04098,94,33.08,-18.53,0.92514,3,91,48.45,-10.32,0.10508,93,29.47,-27.12,0.17398,94,21.72,-29.13,0.72093,3,91,40.71,-22.8,0.18939,93,17.18,-35.17,0.30571,94,8.77,-36.07,0.5049,3,91,26.73,-26.37,0.28786,93,3,-32.49,0.40233,94,-5.13,-32.17,0.30981,3,91,10.48,-22.69,0.49763,93,-10.17,-22.29,0.42531,94,-17.35,-20.85,0.07706,5,89,34.04,-8.37,0.00384,90,15.33,-15.98,0.05966,91,-2.59,-18.69,0.66584,93,-20.33,-13.14,0.2693,94,-26.67,-10.86,0.00136,4,89,20.32,-9.49,0.22674,90,2.34,-11.43,0.45056,91,-9.62,-6.85,0.27229,93,-21.69,0.56,0.05041,3,88,23.52,-9.82,0.10058,89,6.02,-12.65,0.78624,90,-12.01,-8.5,0.11318,3,87,20.92,-12.95,0.20729,88,6.22,-13.54,0.72207,89,-11.51,-10.23,0.07064,5,73,31.39,-45,0.00167,74,13.86,-46.38,0.00658,86,20.6,-13.69,0.17036,87,5.85,-14.25,0.66535,88,-8.91,-13.53,0.15604,5,73,20.5,-41.7,0.04675,74,3.3,-42.15,0.08742,85,23.05,-12.02,0.11429,86,8.43,-12.8,0.61382,87,-6.2,-12.31,0.13771,6,73,26.51,-29.43,0.1386,74,10.36,-30.45,0.31691,75,-5.82,-30.05,0.00273,85,25.63,-26.45,0.18399,86,9.74,-27.4,0.35541,87,-6.18,-26.97,0.00235,6,73,25.03,-13.07,0.08601,74,10.31,-14.03,0.58,75,-4.44,-13.69,0.18616,76,-19.11,-12.07,0.00289,85,19.26,-42.87,0.05892,86,1.96,-43.21,0.08601,5,74,26.82,-12.45,0.02021,75,12.15,-13.56,0.62171,76,-2.57,-13.39,0.35457,85,35.19,-50.8,0.0008,86,17.15,-52.49,0.00272,3,75,31.56,-11.21,0.01702,76,16.98,-12.73,0.41901,77,-1.12,-13.14,0.56397,4,76,31.06,-7.04,0.00741,77,14.06,-12.61,0.65256,78,-4.65,-11.73,0.31303,79,-15.17,-2.59,0.027,6,77,26.16,-9.89,0.11068,78,7.51,-14.17,0.45124,79,-7.42,-12.28,0.3817,80,-16.15,-7.19,0.04542,81,-21.99,-5.29,0.00586,82,-27.65,-2.89,0.0051,5,78,20.17,-11.4,0.0945,79,4.07,-18.29,0.45381,80,-7.41,-16.77,0.22123,81,-14.12,-15.59,0.11871,82,-20.71,-13.84,0.11176,5,78,34.43,-5.34,0.00029,79,18.88,-22.82,0.18199,80,4.96,-26.09,0.18009,81,-2.61,-25.96,0.22071,82,-10.15,-25.17,0.41691,4,79,31.29,-24.11,0.08641,80,16.17,-31.54,0.11109,81,8.08,-32.37,0.19488,82,-0.05,-32.49,0.60762,4,79,42.06,-16.69,0.0403,80,28.83,-28.26,0.06308,81,20.98,-30.2,0.14136,82,12.99,-31.45,0.75526,5,75,48.79,56.37,0.00248,79,45.56,-5.22,0.01218,80,36.05,-18.68,0.02414,81,29.01,-21.29,0.07098,82,21.76,-23.27,0.89022,6,75,35.72,60.61,0.02326,76,27.38,58.45,0.00003,78,38.19,37.93,0.00003,80,44.32,-7.71,0.00094,81,38.2,-11.08,0.00875,82,31.81,-13.9,0.96699,4,75,22.87,62.28,0.05403,76,14.72,61.23,0.00378,78,31.02,48.73,0.00196,82,39.5,-3.47,0.94024,5,74,17.97,54.71,0.00228,75,9.18,54.12,0.10377,76,0.38,54.29,0.01946,78,15.88,53.7,0.00935,82,38.99,12.46,0.86514,5,74,13.12,41.47,0.01497,75,3.2,41.35,0.17374,76,-6.7,42.1,0.04694,78,2.32,49.85,0.02042,82,30.73,23.88,0.74394,8,99,-40.33,-26.5,0.00002,101,-3.59,-48.12,0.00014,73,22.85,28.86,0.00117,74,11.79,27.94,0.0623,75,0.69,27.98,0.29155,76,-10.36,29,0.08165,78,-9.42,42.96,0.03014,82,20.25,32.56,0.53302,10,99,-46.93,-20.92,0.00152,100,-33.69,-38.8,0.00007,101,-12.03,-49.95,0.01075,73,24.29,15.79,0.08859,74,12.09,14.79,0.31412,75,-0.16,14.86,0.36815,76,-12.35,16,0.04119,78,-19.88,35,0.01499,81,11,40.31,0.00023,82,9.19,39.66,0.16038,9,99,-42.44,-17.32,0.01127,100,-31.15,-33.63,0.00198,101,-12.15,-44.2,0.07797,73,15.56,16.51,0.49869,74,3.46,16.27,0.33454,75,-8.63,17.09,0.05221,76,-20.59,18.95,0.00093,78,-23.75,42.85,0.00176,82,15.24,45.99,0.02067,8,99,-36.04,-22.63,0.02936,100,-23.1,-35.74,0.00609,101,-4.04,-42.36,0.21035,73,14.05,29.08,0.62826,74,3.04,28.93,0.12505,75,-7.93,29.73,0.00032,78,-13.75,50.62,0.00002,82,25.97,39.25,0.00056,5,99,-26.88,-24.16,0.04295,100,-14.15,-33.25,0.00942,101,2.76,-36.03,0.32945,73,5.55,40.37,0.56118,74,-4.44,40.91,0.057,5,99,-15.87,-22.15,0.0563,100,-5.02,-26.78,0.01027,101,7.88,-26.08,0.5269,73,-8.71,49.68,0.38892,74,-17.83,51.43,0.01762,5,99,-4.87,-19.68,0.0472,100,3.9,-19.89,0.00215,101,12.62,-15.86,0.76735,73,-23.44,58.47,0.18015,74,-31.74,61.47,0.00315,5,99,5.53,-15.44,0.00721,100,11.54,-11.66,0.01204,101,15.61,-5.03,0.95798,73,-39.36,64.7,0.02269,74,-47.06,69.06,0.00008,4,100,16.08,-3.08,0.61167,101,15.69,4.68,0.38803,73,-54.04,66.34,0.0003,74,-61.54,71.98,0,4,99,19.06,-0.76,0.98444,100,17.6,7.37,0.01556,73,-69.68,62.66,0,74,-77.44,69.67,0,5,67,-4.81,-39.91,0.00608,68,-11.98,-39.91,0.00002,98,20.12,0.55,0.99352,100,11.81,16.3,0.00038,74,-87.96,57.38,0,6,67,-4.3,-35.19,0.07109,68,-11.48,-35.19,0.00065,98,19.96,5.29,0.92226,100,7.95,19.06,0.006,74,-90.33,50.55,0,85,-106.34,-68.86,0,9,67,-3.58,-28.43,0.24138,68,-10.75,-28.43,0.00535,104,11.14,67.95,0.00001,106,-47.13,50.2,0.00013,98,19.74,12.09,0.73065,100,2.43,23.02,0.01966,73,-83.38,32.45,0.0022,74,-93.72,40.77,0,85,-105.98,-57.76,0.00062,8,67,0.8,-22.28,0.40455,68,-6.38,-22.28,0.01864,106,-39.62,50.98,0.0002,98,23.22,18.79,0.54853,100,-0.77,29.86,0.02287,73,-91.27,24.11,0.00408,74,-102.31,33.15,0,85,-111.65,-46.83,0.00113,4,79,25.47,-0.84,0.01886,80,18.67,-7.69,0.03565,81,12.65,-8.83,0.10663,82,6.55,-9.43,0.83886,8,74,42.93,24.44,0.00001,75,31.41,21.78,0.03427,76,19.7,20.14,0.07627,77,12.68,16.82,0.02715,78,6.06,15.71,0.09995,80,9.01,9.01,0.09211,81,4.48,8.66,0.14611,82,-0.06,8.69,0.52413,8,74,30.01,9.02,0.00061,75,17.19,7.55,0.23119,76,4.3,7.2,0.59692,77,-6.22,9.93,0.01323,78,-14.02,17.11,0.0358,80,0.18,27.09,0.00148,81,-2.74,27.44,0.01204,82,-5.62,28.03,0.10872,8,99,-54.57,-16.04,0.00006,101,-20.56,-53.03,0.00041,73,27.61,2.39,0.00412,74,14.23,1.16,0.35999,75,0.78,1.09,0.62995,78,-29.65,25.25,0.00054,81,-1.96,45.05,0.00001,82,-3.31,45.51,0.00492,4,73,22.44,-55.08,0.00003,74,4.07,-55.65,0.00013,86,15.52,-0.15,0.26366,87,1.96,-0.32,0.73619,7,87,19.66,5.59,0.08623,88,6.59,5.03,0.73915,89,-4.81,7.11,0.06187,91,-5.72,23.01,0.00319,92,-2.48,25.39,0.03192,93,-5.54,25.97,0.02328,94,-8.53,26.82,0.05435,8,87,34.77,16.49,0.01219,88,22.59,14.58,0.02584,89,13.49,10.6,0.16705,90,4.27,9.71,0.02463,91,5.45,8.1,0.15348,92,2.91,7.56,0.38667,93,-1.72,7.74,0.12624,94,-6.32,8.32,0.10391,3,91,26.27,1.73,0.05278,93,14.46,-6.83,0.07257,94,8.53,-7.6,0.87465,10,67,-54.57,-29.41,0.00543,104,-39.5,61.82,0.00105,106,-73.09,6.3,0.00035,98,-30.62,4.02,0.02083,99,-29.02,-10.57,0.03832,100,-21.83,-21.84,0.02115,101,-9.31,-29.44,0.24452,73,-6.33,23.13,0.63378,74,-17.77,24.77,0.03454,85,-23.77,-70.93,0.00004,7,67,-64.97,-13.64,0.00015,104,-47.6,44.77,0.00018,106,-64.49,-10.51,0.00005,73,6,-2.83,0.969,74,-7.75,-2.16,0.0065,85,-3.39,-47.81,0.01688,86,-21.03,-46.16,0.00726,9,67,-63.12,9,0.00684,104,-42.62,22.6,0.00654,106,-43.88,-20.05,0.00152,98,-44.43,40.86,0.00375,100,-59.47,-10.38,0.00141,73,-1.57,-36.56,0.14685,74,-18.24,-35.1,0.04075,85,-1.22,-10.8,0.74413,86,-15.65,-9.47,0.0482,11,67,-50.54,31.3,0.00987,104,-27.06,2.26,0.03459,105,-25.05,-10.49,0.0548,106,-18.27,-20.09,0.00663,107,-6.96,-26.25,0.33299,98,-35.08,64.7,0.00227,100,-72.69,11.56,0.00106,73,-25.25,-67.51,0.0051,74,-44.52,-63.87,0,85,-16.49,28.12,0.54982,86,-27.46,30.63,0.00287,2,106,2.8,-0.22,0.9702,107,2.59,1.1,0.0298,1,99,2.94,0.07,1,10,67,-35.33,-18.59,0.12656,104,-18.94,53.79,0.03039,105,-41.64,38.97,0.00023,106,-54.2,17.72,0.00685,98,-13.07,17.41,0.26681,99,-19.64,9.41,0.03118,100,-21.77,0.23,0.09142,101,-19.43,-9.83,0.08817,73,-37.61,10.9,0.31298,85,-52.41,-49.08,0.04539,10,67,-41.51,-33.1,0.01632,104,-27.08,67.3,0.00315,106,-69.88,19.49,0.00092,98,-17.17,2.18,0.07902,99,-16.24,-6,0.07018,100,-12.19,-12.3,0.05615,101,-5.15,-16.53,0.42521,73,-25.22,31.46,0.34232,74,-35.87,34.72,0.00382,85,-45.72,-73.94,0.00291,9,67,-34.93,32.61,0.02806,104,-11.41,3.15,0.16651,105,-11.58,-2.48,0.08383,106,-9.45,-7.14,0.03133,107,-5.09,-10.69,0.45832,98,-19.8,68.17,0.00486,100,-66.13,25.79,0.00208,73,-49.06,-66.16,0.01155,85,-41.44,33.77,0.21347,11,67,-39.36,1.57,0.16975,104,-20.13,33.27,0.12222,105,-33.21,20.22,0.00629,106,-38.64,4.29,0.02413,107,-36.27,-14,0.01577,98,-19.87,36.81,0.10233,99,-34.62,23.48,0.00429,100,-41.3,6.64,0.03355,101,-39.72,-13.13,0.00254,73,-35.8,-20.33,0.26848,85,-41.32,-17.41,0.25064,11,67,-16.92,4.26,0.52212,104,2.47,33.73,0.20178,105,-13.38,31.06,0.00125,106,-25.26,22.49,0.02743,107,-32.78,8.33,0.00099,98,1.98,42.6,0.09731,99,-17.91,38.7,0.00054,100,-32.59,27.5,0.02255,73,-70.19,-19.62,0.06526,74,-85.12,-12.25,0,85,-76.98,-7.97,0.06079,4,67,1.49,-0.18,0.99934,68,-5.69,-0.18,0.00028,98,20.82,40.77,0.00038,74,-110.9,0.62,0,6,67,14.39,-0.85,0.00111,69,0.04,-0.85,0.50151,68,7.21,-0.85,0.49707,98,33.69,41.9,0.00032,100,-12.73,52.24,0,74,-129.79,6.04,0,1,70,3.07,0.49,1,11,67,-20.8,23.15,0.20179,68,-27.97,23.15,0.00023,104,1.26,14.48,0.59121,105,-5.57,13.43,0.00551,106,-10.72,9.82,0.07233,107,-14.04,3.78,0.02056,98,-4.49,60.76,0.01463,99,-32.04,51.83,0.00001,100,-50.94,33.43,0.00554,73,-68.35,-48.91,0.02528,85,-66.43,21.69,0.06289,9,67,-32.75,42.59,0.00028,104,-7.87,-6.44,0.00378,105,-4.01,-9.34,0.07092,107,4.96,-8.87,0.8093,98,-19.03,78.36,0.00015,100,-73.75,32.6,0.00011,73,-54.46,-80.75,0.00039,74,-74.77,-74.51,0,85,-42.69,50.4,0.11508,12,67,-19.24,-22.5,0.21866,68,-26.42,-22.5,0.00012,104,-3.55,59.9,0.01379,105,-30.81,51.49,0.00001,106,-49.68,33.65,0.00343,98,3.4,15.78,0.59852,99,-4.27,15.57,0.00257,100,-10.45,12.31,0.08091,101,-14.94,6.11,0.0027,73,-61.03,20.2,0.06475,74,-72.52,26.62,0,85,-79.31,-51.74,0.01453,11,67,-11.37,-17.09,0.4184,68,-18.55,-17.09,0.00598,104,4.99,55.64,0.01242,105,-21.26,51.66,0,106,-41.11,37.84,0.00313,98,10.44,22.23,0.47098,99,-1,24.54,0.0001,100,-11.28,21.82,0.04331,73,-74.03,13.72,0.03411,74,-86.04,21.3,0,85,-90.8,-41.22,0.01157,10,67,-10.33,15.89,0.48344,68,-17.51,15.89,0.01182,104,10.62,23.12,0.41328,105,-1.26,25.41,0.00008,106,-11.88,22.5,0.03329,98,6.88,55.04,0.01301,99,-19.31,52,0,100,-39.47,38.97,0.00482,73,-82.59,-35.77,0.01761,85,-84.99,12.34,0.02266,10,67,-34.88,20.16,0.12172,104,-13.1,15.48,0.27503,105,-18.77,7.68,0.03434,106,-20.26,-0.97,0.05238,107,-17.53,-10.19,0.14439,98,-18.02,55.84,0.02712,99,-41.77,41.21,0.00017,100,-55.27,19.7,0.00971,73,-46.49,-47.39,0.0622,85,-44.34,13.66,0.27294,11,67,-50.33,10.59,0.06177,104,-29.73,22.81,0.07735,105,-36.91,6.5,0.01171,106,-36.2,-9.7,0.01633,107,-27.66,-25.29,0.0456,98,-31.99,44.21,0.02887,99,-48.79,24.45,0.00057,100,-54.55,1.54,0.01061,73,-21.18,-36.24,0.17483,74,-37.75,-33.07,0.00079,85,-21.54,-5.33,0.57157,10,67,-50.24,-15.29,0.04556,104,-33.24,48.45,0.01836,105,-51.86,27.63,0.00022,106,-58.68,3.12,0.00424,98,-28.29,18.6,0.07395,99,-33.69,3.43,0.01749,100,-31.98,-11.12,0.0342,101,-23.26,-24.61,0.06305,73,-15.84,2.78,0.68643,85,-27.57,-47.14,0.05651,8,75,30.01,9.23,0.0191,76,17.21,7.76,0.16184,77,6.1,6.03,0.50257,78,-4.34,8.54,0.15658,79,-1.89,12.73,0.0102,80,-2.4,14.43,0.01128,81,-6.42,15.04,0.0506,82,-10.36,16.01,0.08784,6,74,38.99,48.67,0.00009,75,29.59,46.27,0.04015,76,20.02,44.69,0.00661,78,23.34,33.15,0.00321,81,27.59,0.36,0.00057,82,22.23,-1.58,0.94937,8,74,28.87,28.31,0.01528,75,17.74,26.87,0.17771,76,6.53,26.4,0.11721,77,2.44,27.2,0.0009,78,0.92,29.37,0.04844,80,18.27,20.29,0.00433,81,14.69,19.08,0.00548,82,11.01,18.19,0.63066,5,78,6.84,-3.92,0.52086,79,-1.34,-4,0.43196,80,-7.61,-1.48,0.04417,81,-12.98,-0.35,0.00047,82,-18.25,1.24,0.00253,3,91,11.83,-8.58,0.44092,93,-2.99,-10.07,0.49318,94,-9.13,-9.31,0.06589,7,87,22.46,30.58,0.09887,88,11.55,29.69,0.06172,89,8.29,28.58,0.01929,91,19.33,20.65,0.00039,92,20.24,14.61,0.04368,93,16.16,13.25,0.0702,94,11.98,12.25,0.70585,6,87,31.66,49.48,0.0189,88,22.36,47.71,0.00236,91,38.38,11.79,0.00822,92,35.12,-0.24,0.00011,93,29.68,-2.83,0.00321,94,24.04,-4.95,0.96721,3,91,37.52,-8.27,0.12576,93,20.43,-20.66,0.20725,94,13.27,-21.9,0.66699,9,67,-70.37,0.93,0.00097,104,-50.92,29.59,0.00072,106,-54.47,-22.39,0.00021,98,-50.49,31.86,0.00037,100,-56.01,-20.66,0.00011,73,11.06,-25.93,0.25459,74,-4.73,-25.61,0.23107,85,8.66,-25.5,0.29183,86,-7.08,-24.97,0.22011,10,67,-59.37,23.27,0.00511,104,-36.92,8.99,0.0141,105,-36.9,-9.07,0.0216,106,-29.61,-23.82,0.00301,107,-15.31,-34.78,0.12344,98,-42.71,55.52,0.00131,100,-70.04,-0.09,0.0006,73,-10.24,-57.27,0.00173,85,-4.04,13.12,0.80982,86,-16.37,14.6,0.01927,13,67,-56.85,-0.22,0.03333,104,-37.69,32.61,0.0267,105,-48.49,11.52,0.00111,106,-48.81,-10.06,0.00597,107,-38.69,-31.41,0.00149,98,-36.94,32.61,0.02398,99,-47.82,11.86,0.00099,100,-48.36,-9.46,0.00909,101,-38.56,-30.67,0.00012,73,-9.07,-21.34,0.46354,74,-24.38,-19.28,0.02495,85,-13.46,-24.28,0.38737,86,-29.01,-21.83,0.02137,11,67,-9.91,-8.62,0.61851,68,-17.08,-8.62,0.00545,104,7.62,47.45,0.03089,105,-15.15,45.61,0.00003,106,-33.01,34.94,0.0059,98,10.72,30.82,0.25443,99,-4.73,32.29,0.00015,100,-17.93,27.27,0.03017,73,-78.03,1.26,0.03671,74,-91.11,9.24,0,85,-91.24,-27.18,0.01776,10,67,-8.77,8.85,0.65645,68,-15.95,8.85,0.00657,104,11.18,30.31,0.23717,105,-4.08,32.05,0.00009,106,-17.24,27.33,0.02206,98,9.41,48.28,0.0265,99,-13.95,47.17,0.00002,100,-32.58,36.86,0.00728,73,-83.45,-24.82,0.02159,85,-89.11,1.31,0.02227,12,67,-20.47,-6.91,0.42153,104,-2.6,44.29,0.08276,105,-22.76,38.09,0.00066,106,-36.72,24.9,0.01486,107,-44.07,5.19,0.00006,98,0.02,31.04,0.25997,99,-14.32,27.54,0.0028,100,-24.62,18.91,0.05088,101,-30.56,5.45,0.00053,73,-62.48,-3.55,0.1098,74,-76.04,3.09,0,85,-73.78,-26.83,0.05615,10,67,-22.66,12.91,0.33147,104,-2.01,24.36,0.35674,105,-13.03,20.68,0.00589,106,-20.55,13.23,0.05041,107,-24.33,2.28,0.01546,98,-4.91,50.37,0.05162,99,-27.62,42.41,0.00036,100,-42.95,26.77,0.0156,73,-63.37,-33.89,0.06605,85,-65.73,4.72,0.10641],"edges":[0,2,2,4,8,10,10,12,12,14,18,20,20,22,22,24,24,26,26,28,28,30,30,32,32,34,34,36,36,38,38,40,40,42,42,44,44,46,46,48,48,50,50,52,52,54,54,56,56,58,58,60,60,62,62,64,64,66,66,68,68,70,70,72,72,74,74,76,76,78,78,80,80,82,82,84,84,86,86,88,88,90,90,92,92,94,94,96,96,98,98,100,100,102,102,104,104,106,106,108,108,110,110,112,112,114,114,116,116,118,118,120,120,122,122,124,124,126,126,128,128,130,130,132,136,138,0,138,32,164,138,190,22,192,14,16,16,18,4,6,6,8,132,134,134,136]}},"traicau":{"traicau":{"path":"14_15/traicau","x":4.69,"y":0.34,"scaleX":1.3,"scaleY":1.3,"width":5,"height":5}},"traicau2":{"traicau":{"path":"14_15/traicau","x":5.01,"y":0.34,"scaleX":1.3,"scaleY":1.3,"rotation":180,"width":5,"height":5}}}},"animations":{"animation":{"slots":{"Bulb Left":{"color":[{"time":0,"color":"ffffffff"},{"time":0.5,"color":"ffffff5c"},{"time":1,"color":"ffffffff"}]},"Bulb Right":{"color":[{"time":0,"color":"ffffff5c"},{"time":0.5,"color":"ffffffff"},{"time":1,"color":"ffffff5c"}]}},"bones":{"3D Tilt":{"translate":[{"time":0,"x":-50,"y":0,"curve":[0.25,0,0.75,1]},{"time":0.5,"x":50,"y":0,"curve":[0.25,0,0.75,1]},{"time":1,"x":-50,"y":0}]},"Tail 2":{"rotate":[{"time":0,"angle":-10,"curve":[0.25,0,0.75,1]},{"time":0.5,"angle":10,"curve":[0.25,0,0.75,1]},{"time":1,"angle":-10}]},"Tail 3":{"rotate":[{"time":0,"angle":-10,"curve":[0.25,0,0.75,1]},{"time":0.5,"angle":10,"curve":[0.25,0,0.75,1]},{"time":1,"angle":-10}]},"Tail 4":{"rotate":[{"time":0,"angle":-10,"curve":[0.25,0,0.75,1]},{"time":0.5,"angle":10,"curve":[0.25,0,0.75,1]},{"time":1,"angle":-10}]},"Fin Left":{"scale":[{"time":0,"x":1,"y":1,"curve":[0.25,0,0.75,1]},{"time":0.1667,"x":0.5,"y":1,"curve":[0.25,0,0.75,1]},{"time":0.3333,"x":1,"y":1,"curve":[0.25,0,0.75,1]},{"time":0.5,"x":0.5,"y":1,"curve":[0.25,0,0.75,1]},{"time":0.6667,"x":1,"y":1,"curve":[0.25,0,0.75,1]},{"time":0.8333,"x":0.5,"y":1,"curve":[0.25,0,0.75,1]},{"time":1,"x":1,"y":1}]},"Fin Right":{"scale":[{"time":0,"x":1,"y":1,"curve":[0.25,0,0.75,1]},{"time":0.1667,"x":0.45,"y":1,"curve":[0.25,0,0.75,1]},{"time":0.3333,"x":1,"y":1,"curve":[0.25,0,0.75,1]},{"time":0.5,"x":0.45,"y":1,"curve":[0.25,0,0.75,1]},{"time":0.6667,"x":1,"y":1,"curve":[0.25,0,0.75,1]},{"time":0.8333,"x":0.45,"y":1,"curve":[0.25,0,0.75,1]},{"time":1,"x":1,"y":1}]},"Beard Left 1":{"rotate":[{"time":0,"angle":0,"curve":[0.25,0,0.75,1]},{"time":0.5,"angle":2.85,"curve":[0.25,0,0.75,1]},{"time":1,"angle":0}]},"Beard Left 10":{"rotate":[{"time":0,"angle":0,"curve":[0.25,0,0.75,1]},{"time":0.5,"angle":2.85,"curve":[0.25,0,0.75,1]},{"time":1,"angle":0}]},"Beard Left 9":{"rotate":[{"time":0,"angle":0,"curve":[0.25,0,0.75,1]},{"time":0.5,"angle":2.85,"curve":[0.25,0,0.75,1]},{"time":1,"angle":0}]},"Beard Left 8":{"rotate":[{"time":0,"angle":0,"curve":[0.25,0,0.75,1]},{"time":0.5,"angle":2.85,"curve":[0.25,0,0.75,1]},{"time":1,"angle":0}]},"Beard Left 7":{"rotate":[{"time":0,"angle":0,"curve":[0.25,0,0.75,1]},{"time":0.5,"angle":2.85,"curve":[0.25,0,0.75,1]},{"time":1,"angle":0}]},"Beard Left 6":{"rotate":[{"time":0,"angle":0,"curve":[0.25,0,0.75,1]},{"time":0.5,"angle":2.85,"curve":[0.25,0,0.75,1]},{"time":1,"angle":0}]},"Beard Left 5":{"rotate":[{"time":0,"angle":0,"curve":[0.25,0,0.75,1]},{"time":0.5,"angle":2.85,"curve":[0.25,0,0.75,1]},{"time":1,"angle":0}]},"Beard Left 4":{"rotate":[{"time":0,"angle":0,"curve":[0.25,0,0.75,1]},{"time":0.5,"angle":2.85,"curve":[0.25,0,0.75,1]},{"time":1,"angle":0}]},"Beard Left 3":{"rotate":[{"time":0,"angle":0,"curve":[0.25,0,0.75,1]},{"time":0.5,"angle":2.85,"curve":[0.25,0,0.75,1]},{"time":1,"angle":0}]},"Beard Left 2":{"rotate":[{"time":0,"angle":0,"curve":[0.25,0,0.75,1]},{"time":0.5,"angle":2.85,"curve":[0.25,0,0.75,1]},{"time":1,"angle":0}]},"Beard Left 11":{"rotate":[{"time":0,"angle":2.56,"curve":[0.25,0,0.75,1]},{"time":0.5,"angle":0,"curve":[0.25,0,0.75,1]},{"time":1,"angle":2.56}]},"Beard Left 20":{"rotate":[{"time":0,"angle":2.56,"curve":[0.25,0,0.75,1]},{"time":0.5,"angle":0,"curve":[0.25,0,0.75,1]},{"time":1,"angle":2.56}]},"Beard Left 19":{"rotate":[{"time":0,"angle":2.56,"curve":[0.25,0,0.75,1]},{"time":0.5,"angle":0,"curve":[0.25,0,0.75,1]},{"time":1,"angle":2.56}]},"Beard Left 18":{"rotate":[{"time":0,"angle":2.56,"curve":[0.25,0,0.75,1]},{"time":0.5,"angle":0,"curve":[0.25,0,0.75,1]},{"time":1,"angle":2.56}]},"Beard Left 17":{"rotate":[{"time":0,"angle":2.56,"curve":[0.25,0,0.75,1]},{"time":0.5,"angle":0,"curve":[0.25,0,0.75,1]},{"time":1,"angle":2.56}]},"Beard Left 16":{"rotate":[{"time":0,"angle":2.56,"curve":[0.25,0,0.75,1]},{"time":0.5,"angle":0,"curve":[0.25,0,0.75,1]},{"time":1,"angle":2.56}]},"Beard Left 15":{"rotate":[{"time":0,"angle":2.56,"curve":[0.25,0,0.75,1]},{"time":0.5,"angle":0,"curve":[0.25,0,0.75,1]},{"time":1,"angle":2.56}]},"Beard Left 14":{"rotate":[{"time":0,"angle":2.56,"curve":[0.25,0,0.75,1]},{"time":0.5,"angle":0,"curve":[0.25,0,0.75,1]},{"time":1,"angle":2.56}]},"Beard Left 13":{"rotate":[{"time":0,"angle":2.56,"curve":[0.25,0,0.75,1]},{"time":0.5,"angle":0,"curve":[0.25,0,0.75,1]},{"time":1,"angle":2.56}]},"Beard Left 12":{"rotate":[{"time":0,"angle":2.56,"curve":[0.25,0,0.75,1]},{"time":0.5,"angle":0,"curve":[0.25,0,0.75,1]},{"time":1,"angle":2.56}]},"Tail 8":{"rotate":[{"time":0,"angle":-10,"curve":[0.25,0,0.75,1]},{"time":0.5,"angle":10,"curve":[0.25,0,0.75,1]},{"time":1,"angle":-10}]},"Tail 7":{"rotate":[{"time":0,"angle":-10,"curve":[0.25,0,0.75,1]},{"time":0.5,"angle":10,"curve":[0.25,0,0.75,1]},{"time":1,"angle":-10}]},"Tail 6":{"rotate":[{"time":0,"angle":-10,"curve":[0.25,0,0.75,1]},{"time":0.5,"angle":10,"curve":[0.25,0,0.75,1]},{"time":1,"angle":-10}]},"Beard Left 30":{"rotate":[{"time":0,"angle":0,"curve":[0.25,0,0.75,1]},{"time":0.5,"angle":2.85,"curve":[0.25,0,0.75,1]},{"time":1,"angle":0}]},"Beard Left 29":{"rotate":[{"time":0,"angle":0,"curve":[0.25,0,0.75,1]},{"time":0.5,"angle":2.85,"curve":[0.25,0,0.75,1]},{"time":1,"angle":0}]},"Beard Left 28":{"rotate":[{"time":0,"angle":0,"curve":[0.25,0,0.75,1]},{"time":0.5,"angle":2.85,"curve":[0.25,0,0.75,1]},{"time":1,"angle":0}]},"Beard Left 27":{"rotate":[{"time":0,"angle":0,"curve":[0.25,0,0.75,1]},{"time":0.5,"angle":2.85,"curve":[0.25,0,0.75,1]},{"time":1,"angle":0}]},"Beard Left 26":{"rotate":[{"time":0,"angle":0,"curve":[0.25,0,0.75,1]},{"time":0.5,"angle":2.85,"curve":[0.25,0,0.75,1]},{"time":1,"angle":0}]},"Beard Left 25":{"rotate":[{"time":0,"angle":0,"curve":[0.25,0,0.75,1]},{"time":0.5,"angle":2.85,"curve":[0.25,0,0.75,1]},{"time":1,"angle":0}]},"Beard Left 24":{"rotate":[{"time":0,"angle":0,"curve":[0.25,0,0.75,1]},{"time":0.5,"angle":2.85,"curve":[0.25,0,0.75,1]},{"time":1,"angle":0}]},"Beard Left 23":{"rotate":[{"time":0,"angle":0,"curve":[0.25,0,0.75,1]},{"time":0.5,"angle":2.85,"curve":[0.25,0,0.75,1]},{"time":1,"angle":0}]},"Beard Left 22":{"rotate":[{"time":0,"angle":0,"curve":[0.25,0,0.75,1]},{"time":0.5,"angle":2.85,"curve":[0.25,0,0.75,1]},{"time":1,"angle":0}]},"Beard Left 21":{"rotate":[{"time":0,"angle":0,"curve":[0.25,0,0.75,1]},{"time":0.5,"angle":2.85,"curve":[0.25,0,0.75,1]},{"time":1,"angle":0}]},"Beard Left 40":{"rotate":[{"time":0,"angle":2.56,"curve":[0.25,0,0.75,1]},{"time":0.5,"angle":0,"curve":[0.25,0,0.75,1]},{"time":1,"angle":2.56}]},"Beard Left 39":{"rotate":[{"time":0,"angle":2.56,"curve":[0.25,0,0.75,1]},{"time":0.5,"angle":0,"curve":[0.25,0,0.75,1]},{"time":1,"angle":2.56}]},"Beard Left 38":{"rotate":[{"time":0,"angle":2.56,"curve":[0.25,0,0.75,1]},{"time":0.5,"angle":0,"curve":[0.25,0,0.75,1]},{"time":1,"angle":2.56}]},"Beard Left 37":{"rotate":[{"time":0,"angle":2.56,"curve":[0.25,0,0.75,1]},{"time":0.5,"angle":0,"curve":[0.25,0,0.75,1]},{"time":1,"angle":2.56}]},"Beard Left 36":{"rotate":[{"time":0,"angle":2.56,"curve":[0.25,0,0.75,1]},{"time":0.5,"angle":0,"curve":[0.25,0,0.75,1]},{"time":1,"angle":2.56}]},"Beard Left 35":{"rotate":[{"time":0,"angle":2.56,"curve":[0.25,0,0.75,1]},{"time":0.5,"angle":0,"curve":[0.25,0,0.75,1]},{"time":1,"angle":2.56}]},"Beard Left 34":{"rotate":[{"time":0,"angle":2.56,"curve":[0.25,0,0.75,1]},{"time":0.5,"angle":0,"curve":[0.25,0,0.75,1]},{"time":1,"angle":2.56}]},"Beard Left 33":{"rotate":[{"time":0,"angle":2.56,"curve":[0.25,0,0.75,1]},{"time":0.5,"angle":0,"curve":[0.25,0,0.75,1]},{"time":1,"angle":2.56}]},"Beard Left 32":{"rotate":[{"time":0,"angle":2.56,"curve":[0.25,0,0.75,1]},{"time":0.5,"angle":0,"curve":[0.25,0,0.75,1]},{"time":1,"angle":2.56}]},"Beard Left 31":{"rotate":[{"time":0,"angle":2.56,"curve":[0.25,0,0.75,1]},{"time":0.5,"angle":0,"curve":[0.25,0,0.75,1]},{"time":1,"angle":2.56}]},"Fin Left2":{"scale":[{"time":0,"x":1,"y":1,"curve":[0.25,0,0.75,1]},{"time":0.1667,"x":0.75,"y":1,"curve":[0.25,0,0.75,1]},{"time":0.3333,"x":1,"y":1,"curve":[0.25,0,0.75,1]},{"time":0.5,"x":0.75,"y":1,"curve":[0.25,0,0.75,1]},{"time":0.6667,"x":1,"y":1,"curve":[0.25,0,0.75,1]},{"time":0.8333,"x":0.75,"y":1,"curve":[0.25,0,0.75,1]},{"time":1,"x":1,"y":1}]},"Fin Right2":{"scale":[{"time":0,"x":1,"y":1,"curve":[0.25,0,0.75,1]},{"time":0.1667,"x":0.75,"y":1,"curve":[0.25,0,0.75,1]},{"time":0.3333,"x":1,"y":1,"curve":[0.25,0,0.75,1]},{"time":0.5,"x":0.75,"y":1,"curve":[0.25,0,0.75,1]},{"time":0.6667,"x":1,"y":1,"curve":[0.25,0,0.75,1]},{"time":0.8333,"x":0.75,"y":1,"curve":[0.25,0,0.75,1]},{"time":1,"x":1,"y":1}]},"Bulb Left":{"scale":[{"time":0,"x":1.2,"y":1.2}]},"Bulb Right":{"scale":[{"time":0,"x":1.2,"y":1.2}]}}}}},[0]]],0,0,[0],[-1],[0]]