[1,["c7t6R4dtlD0KIPRWmk5xQF","22DpVREv9N86CygYYDrlLl","6aHRP3waZLa4q/Z6LIJdCx","35gZbvt2pHuK79WWHWCqcX","c5gtuVomZJPrAGriV+6v1j","c5Ly+dK7ZKhIxmZocMZvgc"],["value"],[["cc.AnimationClip",["_name","_duration","sample","wrapMode","curveData"],-1,11]],[[0,0,1,2,3,4,5]],[[0,"randomSprite2",1.2,10,2,[{},"comps",11,[{},"cc.Sprite",11,[{},"spriteFrame",12,[[[{"frame":0},"value",6,0],[{"frame":0.1},"value",6,1],[{"frame":0.2},"value",6,2],[{"frame":0.3},"value",6,3],[{"frame":0.4},"value",6,4],[{"frame":0.5},"value",6,5],[{"frame":0.6},"value",6,6],[{"frame":0.7},"value",6,7],[{"frame":0.8},"value",6,8],[{"frame":0.9},"value",6,9],[{"frame":1},"value",6,10],[{"frame":1.1},"value",6,11]],11,11,11,11,11,11,11,11,11,11,11,11]]]]]],0,0,[0,0,0,0,0,0,0,0,0,0,0,0],[0,0,0,0,0,0,0,0,0,0,0,0],[1,0,2,3,4,0,5,1,4,0,3,2]]