[1,["ecpdLyjvZBwrvm+cedCcQy","42cA8gxplE8pKtUM8DWXp+","dbEWUhTHtFM5Z8RPMIoG/u","69mJRt87VPHZvCJcJ0Z3kY","e97GVMl6JHh5Ml5qEDdSGa","f0BIwQ8D5Ml7nTNQbh1YlS","29FYIk+N1GYaeWH/q1NxQO","ceWAQfneRA+48yZHDzrM4J","e1vkEuOYtP07z2+EN3P6jh","46oyaAgQpE/qNpt6vf04C8","dfn9O8E2hJkLez4cK2qua9","f74Qn1LZpMuZHP+e1fX+mZ","55S/4ZhH1APpiY67ifqgYN","a2MjXRFdtLlYQ5ouAFv/+R","64H6Mif6dM3Ixq8WUvNHzU","c9VupEoCxGbIrIXOJwwOth","01Nv1oiSFBnqzKJF/nEChs","dcY4AxUPhL8YlANudUAGXH","81Trs1QIRHhquKMYIVx/OI","bahR5kXmxDKZ4P9VEr5qOV"],["node","_spriteFrame","_N$file","_textureSetter","root","_N$target","_N$normalSprite","_N$pressedSprite","_N$hoverSprite","_N$disabledSprite","toggleAuto","edbCaptcha","edbUserPass","edbUserName","data","_parent","checkMark"],[["cc.Node",["_name","_active","_prefab","_contentSize","_components","_parent","_trs","_children","_color","_anchorPoint"],1,4,5,9,1,7,2,5,5],["cc.Label",["_fontSize","_isSystemFontUsed","_lineHeight","_N$horizontalAlign","_N$verticalAlign","_string","_enableWrapText","_N$overflow","_N$cacheMode","_styleFlags","node","_materials","_N$file"],-7,1,3,6],["cc.Sprite",["_sizeMode","_type","_isTrimmedMode","_materials","node","_spriteFrame"],0,3,1,6],["cc.Button",["_N$transition","node","clickEvents","_N$target","_N$normalColor","_N$pressedColor","_N$disabledColor","_N$normalSprite","_N$pressedSprite","_N$hoverSprite","_N$disabledSprite"],2,1,9,1,5,5,5,6,6,6,6],["cc.Widget",["_alignFlags","_left","alignMode","_originalWidth","_originalHeight","_top","_right","node"],-4,1],["cc.Node",["_name","_active","_parent","_components","_prefab","_contentSize","_trs","_children"],1,1,2,4,5,7,2],["cc.Node",["_name","_active","_parent","_components","_prefab","_contentSize","_color","_anchorPoint","_trs"],1,1,12,4,5,5,5,7],["cc.PrefabInfo",["fileId","root","asset"],2,1,1],["cc.EditBox",["maxLength","_N$inputMode","_N$inputFlag","node","_N$textLabel","_N$placeholderLabel","_N$background","editingReturn"],0,1,1,1,1,9],"cc.SpriteFrame",["cc.Prefab",["_name","optimizationPolicy"],1],["cc.BlockInputEvents",["node"],3,1],["e56a3rpsfFIZJduek0yoMKh",["node","edbUserName","edbUserPass","edbCaptcha","toggleAuto"],3,1,1,1,1,1],["5a7c8LGqhdCRY2I3VQ6smot",["node"],3,1],["cc.Layout",["_resize","_N$layoutType","_N$spacingY","node","_layoutSize"],0,1,5],["cc.ClickEvent",["_componentId","handler","target"],1,1],["a2595sv7PBBRqClGtm5M/Gc",["node"],3,1],["cc.LabelOutline",["_width","node","_color"],2,1,5],["cc.Toggle",["_N$transition","node","_N$normalColor","_N$target","checkEvents"],2,1,5,1,9]],[[7,0,1,2,2],[15,0,1,2,3],[0,0,5,4,2,3,6,2],[4,2,0,1,3,4,7,6],[0,0,5,7,4,2,3,6,2],[2,4,3,5,1],[6,0,2,3,4,5,2],[6,0,1,2,3,4,6,5,7,8,3],[6,0,2,3,4,6,5,7,8,2],[2,0,4,3,5,2],[2,1,0,4,3,3],[1,5,0,2,6,1,3,4,7,10,11,9],[5,0,2,7,3,4,5,6,2],[5,0,2,3,4,5,6,2],[4,2,0,3,4,7,5],[10,0,1,3],[0,0,7,4,2,3,2],[0,0,5,7,4,2,3,9,6,2],[0,0,5,7,2,3,6,2],[0,0,7,4,2,3,6,2],[0,0,1,5,4,2,3,6,3],[0,0,5,4,2,3,2],[0,0,1,5,4,2,8,3,6,3],[0,0,5,4,2,8,3,6,2],[5,0,1,2,7,3,4,5,6,3],[11,0,1],[12,0,1,2,3,4,1],[2,1,4,3,5,2],[2,0,2,3,3],[13,0,1],[7,1,2,1],[7,0,1,2],[14,0,1,2,3,4,4],[3,0,1,2,4,5,6,3,7,8,9,10,2],[3,0,1,4,5,6,3,7,8,9,10,2],[3,0,1,2,3,2],[3,1,2,3,1],[3,1,2,1],[4,0,1,5,7,4],[4,2,0,1,6,3,4,7,7],[16,0,1],[1,5,0,2,6,1,3,4,8,10,11,12,9],[1,0,2,6,1,3,4,7,10,11,8],[1,0,2,6,1,3,4,7,8,10,9],[1,0,2,6,1,3,4,7,10,8],[1,5,0,1,3,4,10,11,12,6],[1,5,0,2,1,8,10,11,12,6],[1,5,0,2,1,9,10,11,12,6],[17,0,1,2,2],[8,0,1,3,4,5,6,3],[8,0,2,1,3,7,4,5,6,4],[8,0,1,3,7,4,5,6,3],[18,0,1,2,3,4,2]],[[[{"name":"btnDangNhap","rect":[0,0,430,89],"offset":[0,0],"originalSize":[430,89],"capInsets":[50,0,50,0]}],[9],0,[0],[3],[7]],[[{"name":"titleDangNhap","rect":[0,0,293,68],"offset":[0,0],"originalSize":[293,68],"capInsets":[0,0,0,0]}],[9],0,[0],[3],[8]],[[[15,"DangNhap",2],[16,"DangNhap",[-10,-11,-12,-13],[[25,-2],[26,-7,-6,-5,-4,-3],[5,-8,[38],39],[29,-9]],[30,-1,0],[5,720,1280]],[17,"Content",1,[-15,-16,-17,-18,-19,-20,-21],[[32,1,2,20,-14,[5,300,702]]],[0,"67oIFI4ApA46a1ziOMc54d",1,0],[5,300,702],[0,0.5,1],[0,260.066,0,0,0,0,1,1,1,1]],[24,"editbox-Captcha",false,2,[-23,-24,-25,-26,-27],[-22],[0,"66KUWPbYRB6oq33MnpAe41",1,0],[5,150,50],[-111.519,-165,0,0,0,0,1,1,1,1]],[12,"editbox-user-name",2,[-29,-30,-31],[-28],[0,"1cRzphMIJFCJBhYMwhWXoi",1,0],[5,380,71],[0,-35.5,0,0,0,0,1,1,1,1]],[12,"editbox-pass",2,[-33,-34,-35],[-32],[0,"f61zl32o1G6YTeL247Firq",1,0],[5,380,71],[0,-126.5,0,0,0,0,1,1,1,1]],[18,"NhoMatKhau",2,[-36,-37,-38,-39],[0,"15H5+IJqJO9JFkd50VbFEj",1,0],[5,120,80],[0,-222,0,0,0,0,1,1,1,1]],[19,"Background",[-41],[[5,-40,[28],29]],[0,"2atpybzSdH7qQ6ADkj8C3h",1,0],[5,430,89],[0,0,0,0,0,0,1,1,1,0]],[4,"buttonClose",1,[-45],[[33,3,-43,[[1,"e56a3rpsfFIZJduek0yoMKh","onClickClose",1]],[4,4293322470],[4,4291348680],[4,3363338360],-42,6,7,8,9],[38,9,18.300999999999988,40.84500000000003,-44]],[0,"28Egi0yzBOToJdr7Roso/o",1,0],[5,74,60],[-304.699,569.155,0,0,0,0,1,1,1,1]],[4,"button-login",2,[7],[[34,3,-46,[4,4293322470],[4,4291348680],[4,3363338360],7,30,31,32,33],[35,3,-47,[[1,"e56a3rpsfFIZJduek0yoMKh","onClickDangNhap",1]],7]],[0,"d64F9xXF9GirDMHfThcIqH",1,0],[5,430,150],[0,-357,0,0,0,0,1,1,1,1]],[4,"BtnQuenPass",2,[-50],[[36,-49,[[1,"e56a3rpsfFIZJduek0yoMKh","onClickQuenPass",1]],-48]],[0,"b9GQBRkWNGZYZQ+CAlnPaf",1,0],[5,350,250],[0,-577,0,0,0,0,1,1,1,1]],[2,"Background",8,[[27,1,-51,[4],5]],[0,"f7jp4Eg3VDoYF07ikHHUwP",1,0],[5,74,59],[0,0,0,0,0,0,1,1,1,0]],[6,"BACKGROUND_SPRITE",4,[[-52,[14,0,45,160,40,-53]],1,4],[0,"ccGxj9BsxORoqG+yNFNCwi",1,0],[5,380,71]],[7,"TEXT_LABEL",false,4,[[-54,[3,0,45,2,158,40,-55]],1,4],[0,"49v7+VaixEpYfoD0rTGcnp",1,0],[4,4278190080],[5,378,50],[0,0,1],[-188,25,0,0,0,0,1,1,1,1]],[8,"PLACEHOLDER_LABEL",4,[[-56,[3,0,45,2,158,40,-57]],1,4],[0,"64uotnF5RCs55ZVTY6NYoR",1,0],[4,4285229931],[5,378,71],[0,0,1],[-188,35.5,0,0,0,0,1,1,1,1]],[6,"BACKGROUND_SPRITE",5,[[-58,[14,0,45,160,40,-59]],1,4],[0,"a40unuHu5Ek5PNzQbk8nk6",1,0],[5,380,71]],[7,"TEXT_LABEL",false,5,[[-60,[3,0,45,2,158,40,-61]],1,4],[0,"d6XZlP03BM2oJRD1LKfBn0",1,0],[4,4278190080],[5,158,40],[0,0,1],[-78,20,0,0,0,0,1,1,1,1]],[8,"PLACEHOLDER_LABEL",5,[[-62,[3,0,45,2,158,40,-63]],1,4],[0,"1dErv8etVB/79cfYkbpKo8",1,0],[4,4285229931],[5,378,71],[0,0,1],[-188,35.5,0,0,0,0,1,1,1,1]],[6,"BACKGROUND_SPRITE",3,[[-64,[39,0,45,-5,-5,160,40,-65]],1,4],[0,"48xf4c4JpMgoUKPEpe33iF",1,0],[5,160,50]],[7,"TEXT_LABEL",false,3,[[-66,[3,0,45,2,158,40,-67]],1,4],[0,"f1SRSoYEhEjbuSmzaivQ9b",1,0],[4,4278190080],[5,158,40],[0,0,1],[-78,20,0,0,0,0,1,1,1,1]],[8,"PLACEHOLDER_LABEL",3,[[-68,[3,0,45,2,158,40,-69]],1,4],[0,"2d4toAl/ZNR44350OBclw3",1,0],[4,4285229931],[5,148,50],[0,0,1],[-73,25,0,0,0,0,1,1,1,1]],[2,"sprite_splash",3,[[9,0,-70,[17],18],[40,-71]],[0,"11XjpmPC9OV7oVBsqZD7Ni",1,0],[5,120,50],[160.027,0,0,0,0,0,1,1,1,1]],[4,"btnRefesh",3,[-73],[[37,-72,[[1,"e56a3rpsfFIZJduek0yoMKh","clickRefeshCaptcha",1]]]],[0,"9du/xokXRFl63l8uJfKBrn",1,0],[5,60,60],[266.042,-0.64,0,0,0,0,1,1,1,1]],[13,"toggle",6,[-75],[31,"c81wniZ0VNQ7UcoJFCxp+O",-74],[5,300,50],[-8.179,0,0,0,0,0,1,1,1,1]],[2,"Background",6,[[9,0,-76,[21],22]],[0,"67lJHbEt5LBKtEBJ0zGrxY",1,0],[5,43.2,40.8],[-160.031,0,0,0,0,0,1,1,1,0]],[20,"Label",false,7,[[41,"ĐĂNG NHẬP",35,45,false,false,1,1,1,-77,[26],27],[48,2,-78,[4,4285491712]]],[0,"c9/DSNWA1F9KStdGg3BkFv",1,0],[5,216.1,60.7],[0,5.658,0,0,0,0,1,1,1,1]],[2,"Title",1,[[5,-79,[0],1]],[0,"d3tStBbzJL14L4r3ekHow9",1,0],[5,293,68],[0,446.216,0,0,0,0,1,1.3,1.3,1]],[2,"LineTop",1,[[9,0,-80,[2],3]],[0,"754pBGaBZBLZeFKw+ZiwyU",1,0],[5,435,4],[0,402.648,0,0,0,0,1,1,1,1]],[10,1,0,12,[10]],[42,25,25,false,false,1,1,1,13,[11]],[11,"Tên Đăng Nhập",25,25,false,false,1,1,1,14,[12]],[49,18,6,4,29,30,28],[10,1,0,15,[13]],[43,25,25,false,false,1,1,1,2,16],[11,"Mật Khẩu",25,25,false,false,1,1,1,17,[14]],[50,18,0,6,5,[[1,"e56a3rpsfFIZJduek0yoMKh","onClickDangNhap",1]],33,34,32],[10,1,0,18,[15]],[44,25,25,false,false,1,1,1,19],[11,"Mã Captcha",25,25,false,false,1,1,1,20,[16]],[21,"refresh",22,[[5,-81,[19],20]],[0,"1cXIBc7lFGfL1sZVEAGd69",1,0],[5,46,46]],[51,15,6,3,[[1,"e56a3rpsfFIZJduek0yoMKh","onClickDangNhap",1]],37,38,36],[52,3,23,[4,4292269782],24,[[1,"e56a3rpsfFIZJduek0yoMKh","onCheckAuto",1]]],[28,2,false,[23]],[13,"checkmark",6,[42],[0,"83SNskgK1ImZ35scow7UH7",1,0],[5,66,51],[-153.801,2.341,0,0,0,0,1,0.6,0.6,1]],[2,"sans_bold-export",6,[[45,"Tự động đăng nhập",30,false,1,1,-82,[24],25]],[0,"95jIocIThGsotHdPgasc9/",1,0],[5,291.61,50.4],[25.482,2.203,0,0,0,0,1,1,1,1]],[22,"sans_bold-export",false,2,[[46,"*Lưu ý: Trường hợp quên mật khẩu, vui lòng liên hệ Admin  để được hỗ trợ.",20,30,false,2,-83,[34],35]],[0,"8ccKf+121HEbbZwhekzMiL",1,0],[4,4278190335],[5,683.26,30],[0,-305,0,0,0,0,1,1,1,1]],[23,"sans_bold-export",10,[[47,"Quên mật khẩu",50,55,false,6,-84,[36],37]],[0,"ddGdkuqt5JR5pGGmAlmA0E",1,0],[4,4290281983],[5,393.3178280709945,69.3],[0,0,0,0,0,0,1,0.5,0.5,1]]],0,[0,4,1,0,0,1,0,10,41,0,11,40,0,12,35,0,13,31,0,0,1,0,0,1,0,0,1,0,-1,26,0,-2,27,0,-3,8,0,-4,2,0,0,2,0,-1,4,0,-2,5,0,-3,3,0,-4,6,0,-5,9,0,-6,45,0,-7,10,0,-1,40,0,-1,18,0,-2,19,0,-3,20,0,-4,21,0,-5,22,0,-1,31,0,-1,12,0,-2,13,0,-3,14,0,-1,35,0,-1,15,0,-2,16,0,-3,17,0,-1,23,0,-2,44,0,-3,24,0,-4,43,0,0,7,0,-1,25,0,5,11,0,0,8,0,0,8,0,-1,11,0,0,9,0,0,9,0,5,10,0,0,10,0,-1,46,0,0,11,0,-1,28,0,0,12,0,-1,29,0,0,13,0,-1,30,0,0,14,0,-1,32,0,0,15,0,-1,33,0,0,16,0,-1,34,0,0,17,0,-1,36,0,0,18,0,-1,37,0,0,19,0,-1,38,0,0,20,0,0,21,0,0,21,0,0,22,0,-1,39,0,4,23,0,-1,41,0,0,24,0,0,25,0,0,25,0,0,26,0,0,27,0,0,39,0,0,44,0,0,45,0,0,46,0,14,1,7,15,9,41,16,42,42,0,43,84],[0,0,0,0,0,0,0,0,0,0,0,0,0,0,0,0,0,0,0,0,0,0,0,0,0,0,0,0,0,0,0,0,0,0,0,0,0,0,0,0,28,29,30,32,33,34,36,37,38,42],[-1,1,-1,1,-1,1,6,7,8,9,-1,-1,-1,-1,-1,-1,-1,-1,1,-1,1,-1,1,-1,-1,2,-1,2,-1,1,6,7,8,9,-1,2,-1,2,-1,1,1,2,2,1,2,2,1,2,2,1],[0,9,0,10,0,11,12,4,5,6,0,0,0,0,0,0,0,0,13,0,14,0,15,0,0,1,0,1,0,16,17,4,5,6,0,1,0,1,0,18,3,2,2,3,2,2,3,1,1,19]]]]